{"pagination": {"limit": 10000, "offset": 0, "count": 377, "total": 377}, "data": [{"open": 24.8, "high": 25.0, "low": 24.6, "close": 24.65, "volume": 3187348.0, "adj_high": null, "adj_low": null, "adj_close": 22.4999, "adj_open": null, "adj_volume": null, "symbol": "CIM/PD", "exchange": "XNYS", "date": "2019-01-16T00:00:00+0000"}, {"open": 24.79, "high": 24.79, "low": 24.64, "close": 24.7, "volume": 472445.0, "adj_high": null, "adj_low": null, "adj_close": 22.5455, "adj_open": null, "adj_volume": null, "symbol": "CIM/PD", "exchange": "XNYS", "date": "2019-01-17T00:00:00+0000"}, {"open": 24.82, "high": 24.85, "low": 24.63, "close": 24.75, "volume": 372301.0, "adj_high": null, "adj_low": null, "adj_close": 22.5911, "adj_open": null, "adj_volume": null, "symbol": "CIM/PD", "exchange": "XNYS", "date": "2019-01-18T00:00:00+0000"}, {"open": 24.8, "high": 24.8, "low": 24.7, "close": 24.7, "volume": 246109.0, "adj_high": null, "adj_low": null, "adj_close": 22.5455, "adj_open": null, "adj_volume": null, "symbol": "CIM/PD", "exchange": "XNYS", "date": "2019-01-22T00:00:00+0000"}, {"open": 24.75, "high": 24.75, "low": 24.7, "close": 24.7, "volume": 82982.0, "adj_high": null, "adj_low": null, "adj_close": 22.5455, "adj_open": null, "adj_volume": null, "symbol": "CIM/PD", "exchange": "XNYS", "date": "2019-01-23T00:00:00+0000"}, {"open": 24.78, "high": 24.84, "low": 24.76, "close": 24.78, "volume": 525099.0, "adj_high": null, "adj_low": null, "adj_close": 22.6185, "adj_open": null, "adj_volume": null, "symbol": "CIM/PD", "exchange": "XNYS", "date": "2019-01-24T00:00:00+0000"}, {"open": 24.78, "high": 24.93, "low": 24.78, "close": 24.93, "volume": 308343.0, "adj_high": null, "adj_low": null, "adj_close": 22.7554, "adj_open": null, "adj_volume": null, "symbol": "CIM/PD", "exchange": "XNYS", "date": "2019-01-25T00:00:00+0000"}, {"open": 24.9, "high": 24.95, "low": 24.82, "close": 24.83, "volume": 167371.0, "adj_high": null, "adj_low": null, "adj_close": 22.6642, "adj_open": null, "adj_volume": null, "symbol": "CIM/PD", "exchange": "XNYS", "date": "2019-01-28T00:00:00+0000"}, {"open": 24.87, "high": 24.9, "low": 24.8, "close": 24.82, "volume": 160878.0, "adj_high": null, "adj_low": null, "adj_close": 22.655, "adj_open": null, "adj_volume": null, "symbol": "CIM/PD", "exchange": "XNYS", "date": "2019-01-29T00:00:00+0000"}, {"open": 24.86, "high": 24.94, "low": 24.84, "close": 24.93, "volume": 180237.0, "adj_high": null, "adj_low": null, "adj_close": 22.7554, "adj_open": null, "adj_volume": null, "symbol": "CIM/PD", "exchange": "XNYS", "date": "2019-01-30T00:00:00+0000"}, {"open": 24.95, "high": 25.46, "low": 24.94, "close": 25.46, "volume": 922712.0, "adj_high": null, "adj_low": null, "adj_close": 23.2392, "adj_open": null, "adj_volume": null, "symbol": "CIM/PD", "exchange": "XNYS", "date": "2019-01-31T00:00:00+0000"}, {"open": 25.39, "high": 25.39, "low": 25.03, "close": 25.1, "volume": 118379.0, "adj_high": null, "adj_low": null, "adj_close": 22.9106, "adj_open": null, "adj_volume": null, "symbol": "CIM/PD", "exchange": "XNYS", "date": "2019-02-01T00:00:00+0000"}, {"open": 25.125, "high": 25.2, "low": 25.04, "close": 25.1, "volume": 157262.0, "adj_high": null, "adj_low": null, "adj_close": 22.9106, "adj_open": null, "adj_volume": null, "symbol": "CIM/PD", "exchange": "XNYS", "date": "2019-02-04T00:00:00+0000"}, {"open": 25.08, "high": 25.14, "low": 25.045, "close": 25.07, "volume": 68208.0, "adj_high": null, "adj_low": null, "adj_close": 22.8832, "adj_open": null, "adj_volume": null, "symbol": "CIM/PD", "exchange": "XNYS", "date": "2019-02-05T00:00:00+0000"}, {"open": 25.09, "high": 25.096, "low": 24.9901, "close": 25.07, "volume": 64893.0, "adj_high": null, "adj_low": null, "adj_close": 22.8832, "adj_open": null, "adj_volume": null, "symbol": "CIM/PD", "exchange": "XNYS", "date": "2019-02-06T00:00:00+0000"}, {"open": 25.07, "high": 25.07, "low": 24.97, "close": 25.03, "volume": 46051.0, "adj_high": null, "adj_low": null, "adj_close": 22.8467, "adj_open": null, "adj_volume": null, "symbol": "CIM/PD", "exchange": "XNYS", "date": "2019-02-07T00:00:00+0000"}, {"open": 25.03, "high": 25.09, "low": 25.0, "close": 25.09, "volume": 66215.0, "adj_high": null, "adj_low": null, "adj_close": 22.9015, "adj_open": null, "adj_volume": null, "symbol": "CIM/PD", "exchange": "XNYS", "date": "2019-02-08T00:00:00+0000"}, {"open": 25.09, "high": 25.13, "low": 25.07, "close": 25.1, "volume": 34904.0, "adj_high": null, "adj_low": null, "adj_close": 22.9106, "adj_open": null, "adj_volume": null, "symbol": "CIM/PD", "exchange": "XNYS", "date": "2019-02-11T00:00:00+0000"}, {"open": 25.1, "high": 25.15, "low": 25.04, "close": 25.05, "volume": 74050.0, "adj_high": null, "adj_low": null, "adj_close": 22.865, "adj_open": null, "adj_volume": null, "symbol": "CIM/PD", "exchange": "XNYS", "date": "2019-02-12T00:00:00+0000"}, {"open": 25.1, "high": 25.13, "low": 25.05, "close": 25.1005, "volume": 37717.0, "adj_high": null, "adj_low": null, "adj_close": 22.9111, "adj_open": null, "adj_volume": null, "symbol": "CIM/PD", "exchange": "XNYS", "date": "2019-02-13T00:00:00+0000"}, {"open": 25.1, "high": 25.14, "low": 25.06, "close": 25.1, "volume": 67262.0, "adj_high": null, "adj_low": null, "adj_close": 22.9106, "adj_open": null, "adj_volume": null, "symbol": "CIM/PD", "exchange": "XNYS", "date": "2019-02-14T00:00:00+0000"}, {"open": 25.11, "high": 25.23, "low": 25.09, "close": 25.19, "volume": 76014.0, "adj_high": null, "adj_low": null, "adj_close": 22.9928, "adj_open": null, "adj_volume": null, "symbol": "CIM/PD", "exchange": "XNYS", "date": "2019-02-15T00:00:00+0000"}, {"open": 25.2, "high": 25.3, "low": 25.14, "close": 25.18, "volume": 76690.0, "adj_high": null, "adj_low": null, "adj_close": 22.9836, "adj_open": null, "adj_volume": null, "symbol": "CIM/PD", "exchange": "XNYS", "date": "2019-02-19T00:00:00+0000"}, {"open": 25.19, "high": 25.2, "low": 25.08, "close": 25.14, "volume": 75288.0, "adj_high": null, "adj_low": null, "adj_close": 22.9471, "adj_open": null, "adj_volume": null, "symbol": "CIM/PD", "exchange": "XNYS", "date": "2019-02-20T00:00:00+0000"}, {"open": 25.12, "high": 25.15, "low": 25.06, "close": 25.1, "volume": 26770.0, "adj_high": null, "adj_low": null, "adj_close": 22.9106, "adj_open": null, "adj_volume": null, "symbol": "CIM/PD", "exchange": "XNYS", "date": "2019-02-21T00:00:00+0000"}, {"open": 25.18, "high": 25.1845, "low": 25.1, "close": 25.16, "volume": 42965.0, "adj_high": null, "adj_low": null, "adj_close": 22.9654, "adj_open": null, "adj_volume": null, "symbol": "CIM/PD", "exchange": "XNYS", "date": "2019-02-22T00:00:00+0000"}, {"open": 25.18, "high": 25.24, "low": 25.12, "close": 25.16, "volume": 42007.0, "adj_high": null, "adj_low": null, "adj_close": 22.9654, "adj_open": null, "adj_volume": null, "symbol": "CIM/PD", "exchange": "XNYS", "date": "2019-02-25T00:00:00+0000"}, {"open": 25.1568, "high": 25.2, "low": 25.12, "close": 25.16, "volume": 35177.0, "adj_high": null, "adj_low": null, "adj_close": 22.9654, "adj_open": null, "adj_volume": null, "symbol": "CIM/PD", "exchange": "XNYS", "date": "2019-02-26T00:00:00+0000"}, {"open": 25.159, "high": 25.17, "low": 25.12, "close": 25.13, "volume": 55429.0, "adj_high": null, "adj_low": null, "adj_close": 22.938, "adj_open": null, "adj_volume": null, "symbol": "CIM/PD", "exchange": "XNYS", "date": "2019-02-27T00:00:00+0000"}, {"open": 25.15, "high": 25.185, "low": 25.07, "close": 25.1, "volume": 67603.0, "adj_high": null, "adj_low": null, "adj_close": 22.9106, "adj_open": null, "adj_volume": null, "symbol": "CIM/PD", "exchange": "XNYS", "date": "2019-02-28T00:00:00+0000"}, {"open": 25.2, "high": 25.2, "low": 25.16, "close": 25.2, "volume": 29885.0, "adj_high": null, "adj_low": null, "adj_close": 23.0019, "adj_open": null, "adj_volume": null, "symbol": "CIM/PD", "exchange": "XNYS", "date": "2019-03-01T00:00:00+0000"}, {"open": 25.2, "high": 25.3, "low": 25.16, "close": 25.17, "volume": 31031.0, "adj_high": null, "adj_low": null, "adj_close": 22.9745, "adj_open": null, "adj_volume": null, "symbol": "CIM/PD", "exchange": "XNYS", "date": "2019-03-04T00:00:00+0000"}, {"open": 25.24, "high": 25.25, "low": 25.17, "close": 25.25, "volume": 24337.0, "adj_high": null, "adj_low": null, "adj_close": 23.0475, "adj_open": null, "adj_volume": null, "symbol": "CIM/PD", "exchange": "XNYS", "date": "2019-03-05T00:00:00+0000"}, {"open": 25.22, "high": 25.22, "low": 25.15, "close": 25.18, "volume": 73638.0, "adj_high": null, "adj_low": null, "adj_close": 22.9836, "adj_open": null, "adj_volume": null, "symbol": "CIM/PD", "exchange": "XNYS", "date": "2019-03-06T00:00:00+0000"}, {"open": 25.15, "high": 25.249, "low": 25.15, "close": 25.175, "volume": 29159.0, "adj_high": null, "adj_low": null, "adj_close": 22.9791, "adj_open": null, "adj_volume": null, "symbol": "CIM/PD", "exchange": "XNYS", "date": "2019-03-07T00:00:00+0000"}, {"open": 25.18, "high": 25.2, "low": 25.13, "close": 25.18, "volume": 55025.0, "adj_high": null, "adj_low": null, "adj_close": 22.9836, "adj_open": null, "adj_volume": null, "symbol": "CIM/PD", "exchange": "XNYS", "date": "2019-03-08T00:00:00+0000"}, {"open": 25.22, "high": 25.22, "low": 25.13, "close": 25.15, "volume": 96731.0, "adj_high": null, "adj_low": null, "adj_close": 22.9562, "adj_open": null, "adj_volume": null, "symbol": "CIM/PD", "exchange": "XNYS", "date": "2019-03-11T00:00:00+0000"}, {"open": 25.17, "high": 25.2, "low": 25.15, "close": 25.1995, "volume": 24707.0, "adj_high": null, "adj_low": null, "adj_close": 23.0014, "adj_open": null, "adj_volume": null, "symbol": "CIM/PD", "exchange": "XNYS", "date": "2019-03-12T00:00:00+0000"}, {"open": 25.21, "high": 25.32, "low": 25.2, "close": 25.24, "volume": 19257.0, "adj_high": null, "adj_low": null, "adj_close": 23.0384, "adj_open": null, "adj_volume": null, "symbol": "CIM/PD", "exchange": "XNYS", "date": "2019-03-13T00:00:00+0000"}, {"open": 25.21, "high": 25.25, "low": 25.15, "close": 25.2, "volume": 65734.0, "adj_high": null, "adj_low": null, "adj_close": 23.0019, "adj_open": null, "adj_volume": null, "symbol": "CIM/PD", "exchange": "XNYS", "date": "2019-03-14T00:00:00+0000"}, {"open": 25.2, "high": 25.2, "low": 25.15, "close": 25.15, "volume": 24978.0, "adj_high": null, "adj_low": null, "adj_close": 22.9562, "adj_open": null, "adj_volume": null, "symbol": "CIM/PD", "exchange": "XNYS", "date": "2019-03-15T00:00:00+0000"}, {"open": 25.21, "high": 25.29, "low": 25.1662, "close": 25.21, "volume": 47102.0, "adj_high": null, "adj_low": null, "adj_close": 23.011, "adj_open": null, "adj_volume": null, "symbol": "CIM/PD", "exchange": "XNYS", "date": "2019-03-18T00:00:00+0000"}, {"open": 25.27, "high": 25.27, "low": 25.16, "close": 25.16, "volume": 25825.0, "adj_high": null, "adj_low": null, "adj_close": 22.9654, "adj_open": null, "adj_volume": null, "symbol": "CIM/PD", "exchange": "XNYS", "date": "2019-03-19T00:00:00+0000"}, {"open": 25.18, "high": 25.35, "low": 25.18, "close": 25.3, "volume": 122071.0, "adj_high": null, "adj_low": null, "adj_close": 23.0932, "adj_open": null, "adj_volume": null, "symbol": "CIM/PD", "exchange": "XNYS", "date": "2019-03-20T00:00:00+0000"}, {"open": 25.25, "high": 25.5, "low": 25.25, "close": 25.45, "volume": 41895.0, "adj_high": null, "adj_low": null, "adj_close": 23.2301, "adj_open": null, "adj_volume": null, "symbol": "CIM/PD", "exchange": "XNYS", "date": "2019-03-21T00:00:00+0000"}, {"open": 25.34, "high": 25.3947, "low": 25.2193, "close": 25.25, "volume": 36712.0, "adj_high": null, "adj_low": null, "adj_close": 23.0475, "adj_open": null, "adj_volume": null, "symbol": "CIM/PD", "exchange": "XNYS", "date": "2019-03-22T00:00:00+0000"}, {"open": 25.26, "high": 25.3127, "low": 25.26, "close": 25.27, "volume": 34522.0, "adj_high": null, "adj_low": null, "adj_close": 23.0658, "adj_open": null, "adj_volume": null, "symbol": "CIM/PD", "exchange": "XNYS", "date": "2019-03-25T00:00:00+0000"}, {"open": 25.3, "high": 25.33, "low": 25.22, "close": 25.3, "volume": 156818.0, "adj_high": null, "adj_low": null, "adj_close": 23.0932, "adj_open": null, "adj_volume": null, "symbol": "CIM/PD", "exchange": "XNYS", "date": "2019-03-26T00:00:00+0000"}, {"open": 25.33, "high": 25.34, "low": 25.28, "close": 25.31, "volume": 10205.0, "adj_high": null, "adj_low": null, "adj_close": 23.1023, "adj_open": null, "adj_volume": null, "symbol": "CIM/PD", "exchange": "XNYS", "date": "2019-03-27T00:00:00+0000"}, {"open": 25.315, "high": 25.47, "low": 25.315, "close": 25.4502, "volume": 36728.0, "adj_high": null, "adj_low": null, "adj_close": 23.2303, "adj_open": null, "adj_volume": null, "symbol": "CIM/PD", "exchange": "XNYS", "date": "2019-03-28T00:00:00+0000"}, {"open": 25.4347, "high": 25.59, "low": 25.4, "close": 25.59, "volume": 37059.0, "adj_high": null, "adj_low": null, "adj_close": 23.3579, "adj_open": null, "adj_volume": null, "symbol": "CIM/PD", "exchange": "XNYS", "date": "2019-03-29T00:00:00+0000"}, {"open": 25.4375, "high": 25.62, "low": 25.39, "close": 25.59, "volume": 45267.0, "adj_high": null, "adj_low": null, "adj_close": 23.3579, "adj_open": null, "adj_volume": null, "symbol": "CIM/PD", "exchange": "XNYS", "date": "2019-04-01T00:00:00+0000"}, {"open": 25.55, "high": 25.615, "low": 25.45, "close": 25.605, "volume": 73295.0, "adj_high": null, "adj_low": null, "adj_close": 23.3716, "adj_open": null, "adj_volume": null, "symbol": "CIM/PD", "exchange": "XNYS", "date": "2019-04-02T00:00:00+0000"}, {"open": 25.63, "high": 25.73, "low": 25.565, "close": 25.71, "volume": 47853.0, "adj_high": null, "adj_low": null, "adj_close": 23.4674, "adj_open": null, "adj_volume": null, "symbol": "CIM/PD", "exchange": "XNYS", "date": "2019-04-03T00:00:00+0000"}, {"open": 25.53, "high": 25.73, "low": 25.53, "close": 25.72, "volume": 14029.0, "adj_high": null, "adj_low": null, "adj_close": 23.4765, "adj_open": null, "adj_volume": null, "symbol": "CIM/PD", "exchange": "XNYS", "date": "2019-04-04T00:00:00+0000"}, {"open": 25.73, "high": 25.8, "low": 25.69, "close": 25.7, "volume": 53068.0, "adj_high": null, "adj_low": null, "adj_close": 23.4583, "adj_open": null, "adj_volume": null, "symbol": "CIM/PD", "exchange": "XNYS", "date": "2019-04-05T00:00:00+0000"}, {"open": 25.58, "high": 25.79, "low": 25.58, "close": 25.65, "volume": 14679.0, "adj_high": null, "adj_low": null, "adj_close": 23.4126, "adj_open": null, "adj_volume": null, "symbol": "CIM/PD", "exchange": "XNYS", "date": "2019-04-08T00:00:00+0000"}, {"open": 25.65, "high": 25.6623, "low": 25.61, "close": 25.61, "volume": 19290.0, "adj_high": null, "adj_low": null, "adj_close": 23.3761, "adj_open": null, "adj_volume": null, "symbol": "CIM/PD", "exchange": "XNYS", "date": "2019-04-09T00:00:00+0000"}, {"open": 25.593, "high": 25.71, "low": 25.54, "close": 25.6766, "volume": 25804.0, "adj_high": null, "adj_low": null, "adj_close": 23.4369, "adj_open": null, "adj_volume": null, "symbol": "CIM/PD", "exchange": "XNYS", "date": "2019-04-10T00:00:00+0000"}, {"open": 25.7, "high": 25.8, "low": 25.56, "close": 25.61, "volume": 29228.0, "adj_high": null, "adj_low": null, "adj_close": 23.3761, "adj_open": null, "adj_volume": null, "symbol": "CIM/PD", "exchange": "XNYS", "date": "2019-04-11T00:00:00+0000"}, {"open": 25.57, "high": 25.68, "low": 25.48, "close": 25.68, "volume": 31584.0, "adj_high": null, "adj_low": null, "adj_close": 23.44, "adj_open": null, "adj_volume": null, "symbol": "CIM/PD", "exchange": "XNYS", "date": "2019-04-12T00:00:00+0000"}, {"open": 25.73, "high": 25.8182, "low": 25.701, "close": 25.8024, "volume": 8944.0, "adj_high": null, "adj_low": null, "adj_close": 23.5517, "adj_open": null, "adj_volume": null, "symbol": "CIM/PD", "exchange": "XNYS", "date": "2019-04-15T00:00:00+0000"}, {"open": 25.72, "high": 25.9, "low": 25.57, "close": 25.88, "volume": 120019.0, "adj_high": null, "adj_low": null, "adj_close": 23.6226, "adj_open": null, "adj_volume": null, "symbol": "CIM/PD", "exchange": "XNYS", "date": "2019-04-16T00:00:00+0000"}, {"open": 25.731, "high": 25.85, "low": 25.64, "close": 25.8, "volume": 91172.0, "adj_high": null, "adj_low": null, "adj_close": 23.5495, "adj_open": null, "adj_volume": null, "symbol": "CIM/PD", "exchange": "XNYS", "date": "2019-04-17T00:00:00+0000"}, {"open": 25.79, "high": 25.85, "low": 25.65, "close": 25.8, "volume": 75709.0, "adj_high": null, "adj_low": null, "adj_close": 23.5495, "adj_open": null, "adj_volume": null, "symbol": "CIM/PD", "exchange": "XNYS", "date": "2019-04-18T00:00:00+0000"}, {"open": 25.7, "high": 25.8, "low": 25.64, "close": 25.8, "volume": 17537.0, "adj_high": null, "adj_low": null, "adj_close": 23.5495, "adj_open": null, "adj_volume": null, "symbol": "CIM/PD", "exchange": "XNYS", "date": "2019-04-22T00:00:00+0000"}, {"open": 25.83, "high": 25.875, "low": 25.8, "close": 25.85, "volume": 44479.0, "adj_high": null, "adj_low": null, "adj_close": 23.5952, "adj_open": null, "adj_volume": null, "symbol": "CIM/PD", "exchange": "XNYS", "date": "2019-04-23T00:00:00+0000"}, {"open": 25.85, "high": 25.85, "low": 25.63, "close": 25.81, "volume": 71095.0, "adj_high": null, "adj_low": null, "adj_close": 23.5587, "adj_open": null, "adj_volume": null, "symbol": "CIM/PD", "exchange": "XNYS", "date": "2019-04-24T00:00:00+0000"}, {"open": 25.72, "high": 25.85, "low": 25.72, "close": 25.72, "volume": 23204.0, "adj_high": null, "adj_low": null, "adj_close": 23.4765, "adj_open": null, "adj_volume": null, "symbol": "CIM/PD", "exchange": "XNYS", "date": "2019-04-25T00:00:00+0000"}, {"open": 25.74, "high": 25.78, "low": 25.69, "close": 25.69, "volume": 25686.0, "adj_high": null, "adj_low": null, "adj_close": 23.4491, "adj_open": null, "adj_volume": null, "symbol": "CIM/PD", "exchange": "XNYS", "date": "2019-04-26T00:00:00+0000"}, {"open": 25.6937, "high": 25.88, "low": 25.6937, "close": 25.8799, "volume": 9594.0, "adj_high": null, "adj_low": null, "adj_close": 23.6225, "adj_open": null, "adj_volume": null, "symbol": "CIM/PD", "exchange": "XNYS", "date": "2019-04-29T00:00:00+0000"}, {"open": 25.8206, "high": 25.96, "low": 25.775, "close": 25.96, "volume": 22248.0, "adj_high": null, "adj_low": null, "adj_close": 23.6956, "adj_open": null, "adj_volume": null, "symbol": "CIM/PD", "exchange": "XNYS", "date": "2019-04-30T00:00:00+0000"}, {"open": 25.82, "high": 25.9121, "low": 25.82, "close": 25.9001, "volume": 25251.0, "adj_high": null, "adj_low": null, "adj_close": 23.6409, "adj_open": null, "adj_volume": null, "symbol": "CIM/PD", "exchange": "XNYS", "date": "2019-05-01T00:00:00+0000"}, {"open": 25.78, "high": 25.99, "low": 25.78, "close": 25.99, "volume": 18993.0, "adj_high": null, "adj_low": null, "adj_close": 23.723, "adj_open": null, "adj_volume": null, "symbol": "CIM/PD", "exchange": "XNYS", "date": "2019-05-02T00:00:00+0000"}, {"open": 25.93, "high": 25.96, "low": 25.9, "close": 25.94, "volume": 18862.0, "adj_high": null, "adj_low": null, "adj_close": 23.6773, "adj_open": null, "adj_volume": null, "symbol": "CIM/PD", "exchange": "XNYS", "date": "2019-05-03T00:00:00+0000"}, {"open": 25.82, "high": 26.01, "low": 25.82, "close": 25.98, "volume": 15836.0, "adj_high": null, "adj_low": null, "adj_close": 23.7138, "adj_open": null, "adj_volume": null, "symbol": "CIM/PD", "exchange": "XNYS", "date": "2019-05-06T00:00:00+0000"}, {"open": 25.98, "high": 26.04, "low": 25.94, "close": 26.02, "volume": 64604.0, "adj_high": null, "adj_low": null, "adj_close": 23.7504, "adj_open": null, "adj_volume": null, "symbol": "CIM/PD", "exchange": "XNYS", "date": "2019-05-07T00:00:00+0000"}, {"open": 25.9629, "high": 26.03, "low": 25.95, "close": 26.02, "volume": 28247.0, "adj_high": null, "adj_low": null, "adj_close": 23.7504, "adj_open": null, "adj_volume": null, "symbol": "CIM/PD", "exchange": "XNYS", "date": "2019-05-08T00:00:00+0000"}, {"open": 25.92, "high": 26.06, "low": 25.82, "close": 26.06, "volume": 41201.0, "adj_high": null, "adj_low": null, "adj_close": 23.7869, "adj_open": null, "adj_volume": null, "symbol": "CIM/PD", "exchange": "XNYS", "date": "2019-05-09T00:00:00+0000"}, {"open": 25.9129, "high": 26.1, "low": 25.9129, "close": 26.1, "volume": 9549.0, "adj_high": null, "adj_low": null, "adj_close": 23.8234, "adj_open": null, "adj_volume": null, "symbol": "CIM/PD", "exchange": "XNYS", "date": "2019-05-10T00:00:00+0000"}, {"open": 25.99, "high": 26.1, "low": 25.99, "close": 26.02, "volume": 56586.0, "adj_high": null, "adj_low": null, "adj_close": 23.7504, "adj_open": null, "adj_volume": null, "symbol": "CIM/PD", "exchange": "XNYS", "date": "2019-05-13T00:00:00+0000"}, {"open": 25.95, "high": 26.18, "low": 25.9, "close": 26.17, "volume": 69319.0, "adj_high": null, "adj_low": null, "adj_close": 23.8873, "adj_open": null, "adj_volume": null, "symbol": "CIM/PD", "exchange": "XNYS", "date": "2019-05-14T00:00:00+0000"}, {"open": 26.09, "high": 26.2, "low": 26.045, "close": 26.07, "volume": 28157.0, "adj_high": null, "adj_low": null, "adj_close": 23.796, "adj_open": null, "adj_volume": null, "symbol": "CIM/PD", "exchange": "XNYS", "date": "2019-05-15T00:00:00+0000"}, {"open": 26.12, "high": 26.14, "low": 26.04, "close": 26.11, "volume": 130070.0, "adj_high": null, "adj_low": null, "adj_close": 23.8325, "adj_open": null, "adj_volume": null, "symbol": "CIM/PD", "exchange": "XNYS", "date": "2019-05-16T00:00:00+0000"}, {"open": 26.09, "high": 26.11, "low": 25.96, "close": 26.02, "volume": 14425.0, "adj_high": null, "adj_low": null, "adj_close": 23.7504, "adj_open": null, "adj_volume": null, "symbol": "CIM/PD", "exchange": "XNYS", "date": "2019-05-17T00:00:00+0000"}, {"open": 26.04, "high": 26.04, "low": 25.97, "close": 26.0, "volume": 11700.0, "adj_high": null, "adj_low": null, "adj_close": 23.7321, "adj_open": null, "adj_volume": null, "symbol": "CIM/PD", "exchange": "XNYS", "date": "2019-05-20T00:00:00+0000"}, {"open": 25.9997, "high": 26.18, "low": 25.9719, "close": 26.16, "volume": 61635.0, "adj_high": null, "adj_low": null, "adj_close": 23.8781, "adj_open": null, "adj_volume": null, "symbol": "CIM/PD", "exchange": "XNYS", "date": "2019-05-21T00:00:00+0000"}, {"open": 26.05, "high": 26.19, "low": 26.05, "close": 26.105, "volume": 27733.0, "adj_high": null, "adj_low": null, "adj_close": 23.8279, "adj_open": null, "adj_volume": null, "symbol": "CIM/PD", "exchange": "XNYS", "date": "2019-05-22T00:00:00+0000"}, {"open": 26.08, "high": 26.17, "low": 26.06, "close": 26.1, "volume": 53842.0, "adj_high": null, "adj_low": null, "adj_close": 23.8234, "adj_open": null, "adj_volume": null, "symbol": "CIM/PD", "exchange": "XNYS", "date": "2019-05-23T00:00:00+0000"}, {"open": 26.06, "high": 26.19, "low": 26.06, "close": 26.19, "volume": 2297.0, "adj_high": null, "adj_low": null, "adj_close": 23.9055, "adj_open": null, "adj_volume": null, "symbol": "CIM/PD", "exchange": "XNYS", "date": "2019-05-24T00:00:00+0000"}, {"open": 26.21, "high": 26.222, "low": 26.06, "close": 26.0601, "volume": 32031.0, "adj_high": null, "adj_low": null, "adj_close": 23.787, "adj_open": null, "adj_volume": null, "symbol": "CIM/PD", "exchange": "XNYS", "date": "2019-05-28T00:00:00+0000"}, {"open": 26.086, "high": 26.27, "low": 26.01, "close": 26.27, "volume": 55839.0, "adj_high": null, "adj_low": null, "adj_close": 23.9785, "adj_open": null, "adj_volume": null, "symbol": "CIM/PD", "exchange": "XNYS", "date": "2019-05-29T00:00:00+0000"}, {"open": 25.46, "high": 25.53, "low": 25.23, "close": 25.47, "volume": 68416.0, "adj_high": null, "adj_low": null, "adj_close": 24.0467, "adj_open": null, "adj_volume": null, "symbol": "CIM/PD", "exchange": "XNYS", "date": "2019-05-30T00:00:00+0000"}, {"open": 25.44, "high": 25.44, "low": 25.07, "close": 25.17, "volume": 145782.0, "adj_high": null, "adj_low": null, "adj_close": 23.7635, "adj_open": null, "adj_volume": null, "symbol": "CIM/PD", "exchange": "XNYS", "date": "2019-05-31T00:00:00+0000"}, {"open": 25.2, "high": 25.37, "low": 25.2, "close": 25.32, "volume": 53367.0, "adj_high": null, "adj_low": null, "adj_close": 23.9051, "adj_open": null, "adj_volume": null, "symbol": "CIM/PD", "exchange": "XNYS", "date": "2019-06-03T00:00:00+0000"}, {"open": 25.38, "high": 25.69, "low": 25.38, "close": 25.48, "volume": 86561.0, "adj_high": null, "adj_low": null, "adj_close": 24.0562, "adj_open": null, "adj_volume": null, "symbol": "CIM/PD", "exchange": "XNYS", "date": "2019-06-04T00:00:00+0000"}, {"open": 25.5, "high": 25.5, "low": 25.41, "close": 25.4725, "volume": 120348.0, "adj_high": null, "adj_low": null, "adj_close": 24.0491, "adj_open": null, "adj_volume": null, "symbol": "CIM/PD", "exchange": "XNYS", "date": "2019-06-05T00:00:00+0000"}, {"open": 25.49, "high": 25.58, "low": 25.43, "close": 25.54, "volume": 17284.0, "adj_high": null, "adj_low": null, "adj_close": 24.1128, "adj_open": null, "adj_volume": null, "symbol": "CIM/PD", "exchange": "XNYS", "date": "2019-06-06T00:00:00+0000"}, {"open": 25.54, "high": 25.68, "low": 25.54, "close": 25.59, "volume": 18310.0, "adj_high": null, "adj_low": null, "adj_close": 24.16, "adj_open": null, "adj_volume": null, "symbol": "CIM/PD", "exchange": "XNYS", "date": "2019-06-07T00:00:00+0000"}, {"open": 25.56, "high": 25.65, "low": 25.55, "close": 25.6, "volume": 25767.0, "adj_high": null, "adj_low": null, "adj_close": 24.1695, "adj_open": null, "adj_volume": null, "symbol": "CIM/PD", "exchange": "XNYS", "date": "2019-06-10T00:00:00+0000"}, {"open": 25.65, "high": 25.65, "low": 25.55, "close": 25.58, "volume": 14607.0, "adj_high": null, "adj_low": null, "adj_close": 24.1506, "adj_open": null, "adj_volume": null, "symbol": "CIM/PD", "exchange": "XNYS", "date": "2019-06-11T00:00:00+0000"}, {"open": 25.57, "high": 25.73, "low": 25.4944, "close": 25.65, "volume": 50757.0, "adj_high": null, "adj_low": null, "adj_close": 24.2167, "adj_open": null, "adj_volume": null, "symbol": "CIM/PD", "exchange": "XNYS", "date": "2019-06-12T00:00:00+0000"}, {"open": 25.5201, "high": 25.7, "low": 25.5201, "close": 25.6924, "volume": 38238.0, "adj_high": null, "adj_low": null, "adj_close": 24.2567, "adj_open": null, "adj_volume": null, "symbol": "CIM/PD", "exchange": "XNYS", "date": "2019-06-13T00:00:00+0000"}, {"open": 25.65, "high": 25.7, "low": 25.58, "close": 25.66, "volume": 14540.0, "adj_high": null, "adj_low": null, "adj_close": 24.2261, "adj_open": null, "adj_volume": null, "symbol": "CIM/PD", "exchange": "XNYS", "date": "2019-06-14T00:00:00+0000"}, {"open": 25.62, "high": 25.6713, "low": 25.46, "close": 25.6, "volume": 47753.0, "adj_high": null, "adj_low": null, "adj_close": 24.1695, "adj_open": null, "adj_volume": null, "symbol": "CIM/PD", "exchange": "XNYS", "date": "2019-06-17T00:00:00+0000"}, {"open": 25.65, "high": 25.65, "low": 25.52, "close": 25.54, "volume": 29395.0, "adj_high": null, "adj_low": null, "adj_close": 24.1128, "adj_open": null, "adj_volume": null, "symbol": "CIM/PD", "exchange": "XNYS", "date": "2019-06-18T00:00:00+0000"}, {"open": 25.52, "high": 25.66, "low": 25.51, "close": 25.66, "volume": 18636.0, "adj_high": null, "adj_low": null, "adj_close": 24.2261, "adj_open": null, "adj_volume": null, "symbol": "CIM/PD", "exchange": "XNYS", "date": "2019-06-19T00:00:00+0000"}, {"open": 25.59, "high": 25.65, "low": 25.57, "close": 25.62, "volume": 37122.0, "adj_high": null, "adj_low": null, "adj_close": 24.1884, "adj_open": null, "adj_volume": null, "symbol": "CIM/PD", "exchange": "XNYS", "date": "2019-06-20T00:00:00+0000"}, {"open": 25.66, "high": 25.7, "low": 25.5, "close": 25.57, "volume": 42450.0, "adj_high": null, "adj_low": null, "adj_close": 24.1411, "adj_open": null, "adj_volume": null, "symbol": "CIM/PD", "exchange": "XNYS", "date": "2019-06-21T00:00:00+0000"}, {"open": 25.53, "high": 25.53, "low": 25.4, "close": 25.45, "volume": 37264.0, "adj_high": null, "adj_low": null, "adj_close": 24.0279, "adj_open": null, "adj_volume": null, "symbol": "CIM/PD", "exchange": "XNYS", "date": "2019-06-24T00:00:00+0000"}, {"open": 25.4155, "high": 25.56, "low": 25.4, "close": 25.49, "volume": 13799.0, "adj_high": null, "adj_low": null, "adj_close": 24.0656, "adj_open": null, "adj_volume": null, "symbol": "CIM/PD", "exchange": "XNYS", "date": "2019-06-25T00:00:00+0000"}, {"open": 25.56, "high": 25.56, "low": 25.36, "close": 25.45, "volume": 63777.0, "adj_high": null, "adj_low": null, "adj_close": 24.0279, "adj_open": null, "adj_volume": null, "symbol": "CIM/PD", "exchange": "XNYS", "date": "2019-06-26T00:00:00+0000"}, {"open": 25.5799, "high": 25.5799, "low": 25.43, "close": 25.47, "volume": 40738.0, "adj_high": null, "adj_low": null, "adj_close": 24.0467, "adj_open": null, "adj_volume": null, "symbol": "CIM/PD", "exchange": "XNYS", "date": "2019-06-27T00:00:00+0000"}, {"open": 25.52, "high": 25.67, "low": 25.5, "close": 25.67, "volume": 18920.0, "adj_high": null, "adj_low": null, "adj_close": 24.2356, "adj_open": null, "adj_volume": null, "symbol": "CIM/PD", "exchange": "XNYS", "date": "2019-06-28T00:00:00+0000"}, {"open": 25.63, "high": 25.7339, "low": 25.5814, "close": 25.7141, "volume": 26315.0, "adj_high": null, "adj_low": null, "adj_close": 24.2772, "adj_open": null, "adj_volume": null, "symbol": "CIM/PD", "exchange": "XNYS", "date": "2019-07-01T00:00:00+0000"}, {"open": 25.6206, "high": 25.76, "low": 25.5, "close": 25.6, "volume": 28129.0, "adj_high": null, "adj_low": null, "adj_close": 24.1695, "adj_open": null, "adj_volume": null, "symbol": "CIM/PD", "exchange": "XNYS", "date": "2019-07-02T00:00:00+0000"}, {"open": 25.6582, "high": 25.68, "low": 25.64, "close": 25.68, "volume": 993.0, "adj_high": null, "adj_low": null, "adj_close": 24.245, "adj_open": null, "adj_volume": null, "symbol": "CIM/PD", "exchange": "XNYS", "date": "2019-07-03T00:00:00+0000"}, {"open": 25.71, "high": 25.71, "low": 25.643, "close": 25.6499, "volume": 7822.0, "adj_high": null, "adj_low": null, "adj_close": 24.2166, "adj_open": null, "adj_volume": null, "symbol": "CIM/PD", "exchange": "XNYS", "date": "2019-07-05T00:00:00+0000"}, {"open": 25.68, "high": 25.7, "low": 25.55, "close": 25.6722, "volume": 9798.0, "adj_high": null, "adj_low": null, "adj_close": 24.2376, "adj_open": null, "adj_volume": null, "symbol": "CIM/PD", "exchange": "XNYS", "date": "2019-07-08T00:00:00+0000"}, {"open": 25.723, "high": 25.7422, "low": 25.7, "close": 25.73, "volume": 815.0, "adj_high": null, "adj_low": null, "adj_close": 24.2922, "adj_open": null, "adj_volume": null, "symbol": "CIM/PD", "exchange": "XNYS", "date": "2019-07-09T00:00:00+0000"}, {"open": 25.698, "high": 25.85, "low": 25.68, "close": 25.76, "volume": 30645.0, "adj_high": null, "adj_low": null, "adj_close": 24.3205, "adj_open": null, "adj_volume": null, "symbol": "CIM/PD", "exchange": "XNYS", "date": "2019-07-10T00:00:00+0000"}, {"open": 25.7794, "high": 25.8189, "low": 25.75, "close": 25.81, "volume": 13398.0, "adj_high": null, "adj_low": null, "adj_close": 24.3677, "adj_open": null, "adj_volume": null, "symbol": "CIM/PD", "exchange": "XNYS", "date": "2019-07-11T00:00:00+0000"}, {"open": 25.8, "high": 25.8538, "low": 25.8, "close": 25.85, "volume": 2364.0, "adj_high": null, "adj_low": null, "adj_close": 24.4055, "adj_open": null, "adj_volume": null, "symbol": "CIM/PD", "exchange": "XNYS", "date": "2019-07-12T00:00:00+0000"}, {"open": 25.79, "high": 25.92, "low": 25.61, "close": 25.75, "volume": 117497.0, "adj_high": null, "adj_low": null, "adj_close": 24.3111, "adj_open": null, "adj_volume": null, "symbol": "CIM/PD", "exchange": "XNYS", "date": "2019-07-15T00:00:00+0000"}, {"open": 25.7993, "high": 25.8399, "low": 25.73, "close": 25.79, "volume": 10043.0, "adj_high": null, "adj_low": null, "adj_close": 24.3489, "adj_open": null, "adj_volume": null, "symbol": "CIM/PD", "exchange": "XNYS", "date": "2019-07-16T00:00:00+0000"}, {"open": 25.7822, "high": 25.85, "low": 25.7822, "close": 25.8281, "volume": 14726.0, "adj_high": null, "adj_low": null, "adj_close": 24.3848, "adj_open": null, "adj_volume": null, "symbol": "CIM/PD", "exchange": "XNYS", "date": "2019-07-17T00:00:00+0000"}, {"open": 25.81, "high": 25.9299, "low": 25.7702, "close": 25.84, "volume": 11031.0, "adj_high": null, "adj_low": null, "adj_close": 24.3961, "adj_open": null, "adj_volume": null, "symbol": "CIM/PD", "exchange": "XNYS", "date": "2019-07-18T00:00:00+0000"}, {"open": 25.94, "high": 25.94, "low": 25.737, "close": 25.81, "volume": 41933.0, "adj_high": null, "adj_low": null, "adj_close": 24.3677, "adj_open": null, "adj_volume": null, "symbol": "CIM/PD", "exchange": "XNYS", "date": "2019-07-19T00:00:00+0000"}, {"open": 25.875, "high": 25.895, "low": 25.8137, "close": 25.87, "volume": 8336.0, "adj_high": null, "adj_low": null, "adj_close": 24.4244, "adj_open": null, "adj_volume": null, "symbol": "CIM/PD", "exchange": "XNYS", "date": "2019-07-22T00:00:00+0000"}, {"open": 25.9, "high": 25.96, "low": 25.89, "close": 25.96, "volume": 20460.0, "adj_high": null, "adj_low": null, "adj_close": 24.5093, "adj_open": null, "adj_volume": null, "symbol": "CIM/PD", "exchange": "XNYS", "date": "2019-07-23T00:00:00+0000"}, {"open": 25.96, "high": 26.018, "low": 25.9, "close": 25.95, "volume": 16732.0, "adj_high": null, "adj_low": null, "adj_close": 24.4999, "adj_open": null, "adj_volume": null, "symbol": "CIM/PD", "exchange": "XNYS", "date": "2019-07-24T00:00:00+0000"}, {"open": 25.97, "high": 26.02, "low": 25.91, "close": 26.0, "volume": 19686.0, "adj_high": null, "adj_low": null, "adj_close": 24.5471, "adj_open": null, "adj_volume": null, "symbol": "CIM/PD", "exchange": "XNYS", "date": "2019-07-25T00:00:00+0000"}, {"open": 25.9645, "high": 26.02, "low": 25.9645, "close": 25.98, "volume": 3145.0, "adj_high": null, "adj_low": null, "adj_close": 24.5282, "adj_open": null, "adj_volume": null, "symbol": "CIM/PD", "exchange": "XNYS", "date": "2019-07-26T00:00:00+0000"}, {"open": 25.97, "high": 25.99, "low": 25.7, "close": 25.885, "volume": 38299.0, "adj_high": null, "adj_low": null, "adj_close": 24.4385, "adj_open": null, "adj_volume": null, "symbol": "CIM/PD", "exchange": "XNYS", "date": "2019-07-29T00:00:00+0000"}, {"open": 25.885, "high": 25.94, "low": 25.8525, "close": 25.89, "volume": 20004.0, "adj_high": null, "adj_low": null, "adj_close": 24.4433, "adj_open": null, "adj_volume": null, "symbol": "CIM/PD", "exchange": "XNYS", "date": "2019-07-30T00:00:00+0000"}, {"open": 25.9379, "high": 26.0, "low": 25.81, "close": 25.82, "volume": 97528.0, "adj_high": null, "adj_low": null, "adj_close": 24.3772, "adj_open": null, "adj_volume": null, "symbol": "CIM/PD", "exchange": "XNYS", "date": "2019-07-31T00:00:00+0000"}, {"open": 25.89, "high": 26.1498, "low": 25.89, "close": 26.05, "volume": 21762.0, "adj_high": null, "adj_low": null, "adj_close": 24.5943, "adj_open": null, "adj_volume": null, "symbol": "CIM/PD", "exchange": "XNYS", "date": "2019-08-01T00:00:00+0000"}, {"open": 26.14, "high": 26.14, "low": 25.9407, "close": 26.09, "volume": 8437.0, "adj_high": null, "adj_low": null, "adj_close": 24.6321, "adj_open": null, "adj_volume": null, "symbol": "CIM/PD", "exchange": "XNYS", "date": "2019-08-02T00:00:00+0000"}, {"open": 25.945, "high": 26.05, "low": 25.94, "close": 26.01, "volume": 31981.0, "adj_high": null, "adj_low": null, "adj_close": 24.5566, "adj_open": null, "adj_volume": null, "symbol": "CIM/PD", "exchange": "XNYS", "date": "2019-08-05T00:00:00+0000"}, {"open": 25.9802, "high": 26.08, "low": 25.9674, "close": 26.08, "volume": 13139.0, "adj_high": null, "adj_low": null, "adj_close": 24.6226, "adj_open": null, "adj_volume": null, "symbol": "CIM/PD", "exchange": "XNYS", "date": "2019-08-06T00:00:00+0000"}, {"open": 26.049, "high": 26.08, "low": 26.0, "close": 26.07, "volume": 32855.0, "adj_high": null, "adj_low": null, "adj_close": 24.6132, "adj_open": null, "adj_volume": null, "symbol": "CIM/PD", "exchange": "XNYS", "date": "2019-08-07T00:00:00+0000"}, {"open": 25.9899, "high": 26.174, "low": 25.9899, "close": 26.167, "volume": 168995.0, "adj_high": null, "adj_low": null, "adj_close": 24.7048, "adj_open": null, "adj_volume": null, "symbol": "CIM/PD", "exchange": "XNYS", "date": "2019-08-08T00:00:00+0000"}, {"open": 26.14, "high": 26.16, "low": 26.06, "close": 26.16, "volume": 7459.0, "adj_high": null, "adj_low": null, "adj_close": 24.6982, "adj_open": null, "adj_volume": null, "symbol": "CIM/PD", "exchange": "XNYS", "date": "2019-08-09T00:00:00+0000"}, {"open": 26.18, "high": 26.24, "low": 26.085, "close": 26.2, "volume": 25976.0, "adj_high": null, "adj_low": null, "adj_close": 24.7359, "adj_open": null, "adj_volume": null, "symbol": "CIM/PD", "exchange": "XNYS", "date": "2019-08-12T00:00:00+0000"}, {"open": 26.16, "high": 26.22, "low": 26.1448, "close": 26.205, "volume": 13129.0, "adj_high": null, "adj_low": null, "adj_close": 24.7407, "adj_open": null, "adj_volume": null, "symbol": "CIM/PD", "exchange": "XNYS", "date": "2019-08-13T00:00:00+0000"}, {"open": 26.07, "high": 26.22, "low": 26.06, "close": 26.15, "volume": 27997.0, "adj_high": null, "adj_low": null, "adj_close": 24.6887, "adj_open": null, "adj_volume": null, "symbol": "CIM/PD", "exchange": "XNYS", "date": "2019-08-14T00:00:00+0000"}, {"open": 26.22, "high": 26.3492, "low": 26.1729, "close": 26.29, "volume": 12557.0, "adj_high": null, "adj_low": null, "adj_close": 24.8209, "adj_open": null, "adj_volume": null, "symbol": "CIM/PD", "exchange": "XNYS", "date": "2019-08-15T00:00:00+0000"}, {"open": 26.19, "high": 26.3251, "low": 26.19, "close": 26.28, "volume": 8483.0, "adj_high": null, "adj_low": null, "adj_close": 24.8115, "adj_open": null, "adj_volume": null, "symbol": "CIM/PD", "exchange": "XNYS", "date": "2019-08-16T00:00:00+0000"}, {"open": 26.3375, "high": 26.34, "low": 26.1901, "close": 26.28, "volume": 38985.0, "adj_high": null, "adj_low": null, "adj_close": 24.8115, "adj_open": null, "adj_volume": null, "symbol": "CIM/PD", "exchange": "XNYS", "date": "2019-08-19T00:00:00+0000"}, {"open": 26.34, "high": 26.38, "low": 26.22, "close": 26.38, "volume": 68639.0, "adj_high": null, "adj_low": null, "adj_close": 24.9059, "adj_open": null, "adj_volume": null, "symbol": "CIM/PD", "exchange": "XNYS", "date": "2019-08-20T00:00:00+0000"}, {"open": 26.37, "high": 26.476, "low": 26.37, "close": 26.41, "volume": 19847.0, "adj_high": null, "adj_low": null, "adj_close": 24.9342, "adj_open": null, "adj_volume": null, "symbol": "CIM/PD", "exchange": "XNYS", "date": "2019-08-21T00:00:00+0000"}, {"open": 26.41, "high": 26.5745, "low": 26.4, "close": 26.56, "volume": 17065.0, "adj_high": null, "adj_low": null, "adj_close": 25.0758, "adj_open": null, "adj_volume": null, "symbol": "CIM/PD", "exchange": "XNYS", "date": "2019-08-22T00:00:00+0000"}, {"open": 26.517, "high": 26.58, "low": 26.47, "close": 26.47, "volume": 8679.0, "adj_high": null, "adj_low": null, "adj_close": 24.9909, "adj_open": null, "adj_volume": null, "symbol": "CIM/PD", "exchange": "XNYS", "date": "2019-08-23T00:00:00+0000"}, {"open": 26.47, "high": 26.4756, "low": 26.32, "close": 26.45, "volume": 81280.0, "adj_high": null, "adj_low": null, "adj_close": 24.972, "adj_open": null, "adj_volume": null, "symbol": "CIM/PD", "exchange": "XNYS", "date": "2019-08-26T00:00:00+0000"}, {"open": 26.3529, "high": 26.5, "low": 26.35, "close": 26.47, "volume": 11221.0, "adj_high": null, "adj_low": null, "adj_close": 24.9909, "adj_open": null, "adj_volume": null, "symbol": "CIM/PD", "exchange": "XNYS", "date": "2019-08-27T00:00:00+0000"}, {"open": 26.47, "high": 26.47, "low": 26.31, "close": 26.35, "volume": 21620.0, "adj_high": null, "adj_low": null, "adj_close": 24.8776, "adj_open": null, "adj_volume": null, "symbol": "CIM/PD", "exchange": "XNYS", "date": "2019-08-28T00:00:00+0000"}, {"open": 26.0, "high": 26.0, "low": 25.75, "close": 25.88, "volume": 30752.0, "adj_high": null, "adj_low": null, "adj_close": 24.9064, "adj_open": null, "adj_volume": null, "symbol": "CIM/PD", "exchange": "XNYS", "date": "2019-08-29T00:00:00+0000"}, {"open": 25.8612, "high": 25.93, "low": 25.78, "close": 25.8, "volume": 50315.0, "adj_high": null, "adj_low": null, "adj_close": 24.8294, "adj_open": null, "adj_volume": null, "symbol": "CIM/PD", "exchange": "XNYS", "date": "2019-08-30T00:00:00+0000"}, {"open": 25.81, "high": 25.8775, "low": 25.81, "close": 25.84, "volume": 21563.0, "adj_high": null, "adj_low": null, "adj_close": 24.8679, "adj_open": null, "adj_volume": null, "symbol": "CIM/PD", "exchange": "XNYS", "date": "2019-09-03T00:00:00+0000"}, {"open": 25.921, "high": 25.95, "low": 25.84, "close": 25.95, "volume": 283988.0, "adj_high": null, "adj_low": null, "adj_close": 24.9738, "adj_open": null, "adj_volume": null, "symbol": "CIM/PD", "exchange": "XNYS", "date": "2019-09-04T00:00:00+0000"}, {"open": 25.9, "high": 25.9, "low": 25.814, "close": 25.814, "volume": 21486.0, "adj_high": null, "adj_low": null, "adj_close": 24.8429, "adj_open": null, "adj_volume": null, "symbol": "CIM/PD", "exchange": "XNYS", "date": "2019-09-05T00:00:00+0000"}, {"open": 25.801, "high": 25.89, "low": 25.7492, "close": 25.85, "volume": 64822.0, "adj_high": null, "adj_low": null, "adj_close": 24.8776, "adj_open": null, "adj_volume": null, "symbol": "CIM/PD", "exchange": "XNYS", "date": "2019-09-06T00:00:00+0000"}, {"open": 25.8745, "high": 25.9695, "low": 25.82, "close": 25.82, "volume": 11234.0, "adj_high": null, "adj_low": null, "adj_close": 24.8487, "adj_open": null, "adj_volume": null, "symbol": "CIM/PD", "exchange": "XNYS", "date": "2019-09-09T00:00:00+0000"}, {"open": 25.83, "high": 25.83, "low": 25.68, "close": 25.68, "volume": 20007.0, "adj_high": null, "adj_low": null, "adj_close": 24.714, "adj_open": null, "adj_volume": null, "symbol": "CIM/PD", "exchange": "XNYS", "date": "2019-09-10T00:00:00+0000"}, {"open": 25.78, "high": 25.78, "low": 25.5777, "close": 25.65, "volume": 24876.0, "adj_high": null, "adj_low": null, "adj_close": 24.6851, "adj_open": null, "adj_volume": null, "symbol": "CIM/PD", "exchange": "XNYS", "date": "2019-09-11T00:00:00+0000"}, {"open": 25.7, "high": 25.72, "low": 25.62, "close": 25.65, "volume": 11199.0, "adj_high": null, "adj_low": null, "adj_close": 24.6851, "adj_open": null, "adj_volume": null, "symbol": "CIM/PD", "exchange": "XNYS", "date": "2019-09-12T00:00:00+0000"}, {"open": 25.85, "high": 25.85, "low": 25.41, "close": 25.6089, "volume": 20796.0, "adj_high": null, "adj_low": null, "adj_close": 24.6455, "adj_open": null, "adj_volume": null, "symbol": "CIM/PD", "exchange": "XNYS", "date": "2019-09-13T00:00:00+0000"}, {"open": 25.48, "high": 25.54, "low": 25.2872, "close": 25.53, "volume": 193104.0, "adj_high": null, "adj_low": null, "adj_close": 24.5696, "adj_open": null, "adj_volume": null, "symbol": "CIM/PD", "exchange": "XNYS", "date": "2019-09-16T00:00:00+0000"}, {"open": 25.56, "high": 25.71, "low": 25.55, "close": 25.62, "volume": 26416.0, "adj_high": null, "adj_low": null, "adj_close": 24.6562, "adj_open": null, "adj_volume": null, "symbol": "CIM/PD", "exchange": "XNYS", "date": "2019-09-17T00:00:00+0000"}, {"open": 25.75, "high": 25.75, "low": 25.65, "close": 25.65, "volume": 3277.0, "adj_high": null, "adj_low": null, "adj_close": 24.6851, "adj_open": null, "adj_volume": null, "symbol": "CIM/PD", "exchange": "XNYS", "date": "2019-09-18T00:00:00+0000"}, {"open": 25.73, "high": 25.86, "low": 25.68, "close": 25.72, "volume": 18706.0, "adj_high": null, "adj_low": null, "adj_close": 24.7524, "adj_open": null, "adj_volume": null, "symbol": "CIM/PD", "exchange": "XNYS", "date": "2019-09-19T00:00:00+0000"}, {"open": 25.7222, "high": 25.78, "low": 25.7222, "close": 25.75, "volume": 7575.0, "adj_high": null, "adj_low": null, "adj_close": 24.7813, "adj_open": null, "adj_volume": null, "symbol": "CIM/PD", "exchange": "XNYS", "date": "2019-09-20T00:00:00+0000"}, {"open": 25.7642, "high": 25.8, "low": 25.68, "close": 25.68, "volume": 22190.0, "adj_high": null, "adj_low": null, "adj_close": 24.714, "adj_open": null, "adj_volume": null, "symbol": "CIM/PD", "exchange": "XNYS", "date": "2019-09-23T00:00:00+0000"}, {"open": 25.67, "high": 25.76, "low": 25.6094, "close": 25.7, "volume": 18599.0, "adj_high": null, "adj_low": null, "adj_close": 24.7332, "adj_open": null, "adj_volume": null, "symbol": "CIM/PD", "exchange": "XNYS", "date": "2019-09-24T00:00:00+0000"}, {"open": 25.654, "high": 25.7568, "low": 25.61, "close": 25.66, "volume": 10304.0, "adj_high": null, "adj_low": null, "adj_close": 24.6947, "adj_open": null, "adj_volume": null, "symbol": "CIM/PD", "exchange": "XNYS", "date": "2019-09-25T00:00:00+0000"}, {"open": 25.6614, "high": 25.7, "low": 25.59, "close": 25.68, "volume": 6240.0, "adj_high": null, "adj_low": null, "adj_close": 24.714, "adj_open": null, "adj_volume": null, "symbol": "CIM/PD", "exchange": "XNYS", "date": "2019-09-26T00:00:00+0000"}, {"open": 25.7657, "high": 25.7695, "low": 25.6551, "close": 25.75, "volume": 8710.0, "adj_high": null, "adj_low": null, "adj_close": 24.7813, "adj_open": null, "adj_volume": null, "symbol": "CIM/PD", "exchange": "XNYS", "date": "2019-09-27T00:00:00+0000"}, {"open": 25.755, "high": 25.94, "low": 25.75, "close": 25.94, "volume": 41899.0, "adj_high": null, "adj_low": null, "adj_close": 24.9642, "adj_open": null, "adj_volume": null, "symbol": "CIM/PD", "exchange": "XNYS", "date": "2019-09-30T00:00:00+0000"}, {"open": 25.8, "high": 25.9, "low": 25.775, "close": 25.83, "volume": 26051.0, "adj_high": null, "adj_low": null, "adj_close": 24.8583, "adj_open": null, "adj_volume": null, "symbol": "CIM/PD", "exchange": "XNYS", "date": "2019-10-01T00:00:00+0000"}, {"open": 25.8, "high": 25.8, "low": 25.6909, "close": 25.76, "volume": 20171.0, "adj_high": null, "adj_low": null, "adj_close": 24.7909, "adj_open": null, "adj_volume": null, "symbol": "CIM/PD", "exchange": "XNYS", "date": "2019-10-02T00:00:00+0000"}, {"open": 25.7101, "high": 25.8, "low": 25.621, "close": 25.72, "volume": 24700.0, "adj_high": null, "adj_low": null, "adj_close": 24.7524, "adj_open": null, "adj_volume": null, "symbol": "CIM/PD", "exchange": "XNYS", "date": "2019-10-03T00:00:00+0000"}, {"open": 25.8, "high": 25.91, "low": 25.8, "close": 25.8453, "volume": 15559.0, "adj_high": null, "adj_low": null, "adj_close": 24.873, "adj_open": null, "adj_volume": null, "symbol": "CIM/PD", "exchange": "XNYS", "date": "2019-10-04T00:00:00+0000"}, {"open": 25.8332, "high": 25.92, "low": 25.782, "close": 25.8873, "volume": 4186.0, "adj_high": null, "adj_low": null, "adj_close": 24.9135, "adj_open": null, "adj_volume": null, "symbol": "CIM/PD", "exchange": "XNYS", "date": "2019-10-07T00:00:00+0000"}, {"open": 25.8, "high": 25.8, "low": 25.74, "close": 25.79, "volume": 26887.0, "adj_high": null, "adj_low": null, "adj_close": 24.8198, "adj_open": null, "adj_volume": null, "symbol": "CIM/PD", "exchange": "XNYS", "date": "2019-10-08T00:00:00+0000"}, {"open": 25.8, "high": 25.8, "low": 25.744, "close": 25.77, "volume": 24878.0, "adj_high": null, "adj_low": null, "adj_close": 24.8006, "adj_open": null, "adj_volume": null, "symbol": "CIM/PD", "exchange": "XNYS", "date": "2019-10-09T00:00:00+0000"}, {"open": 25.77, "high": 25.79, "low": 25.75, "close": 25.78, "volume": 26907.0, "adj_high": null, "adj_low": null, "adj_close": 24.8102, "adj_open": null, "adj_volume": null, "symbol": "CIM/PD", "exchange": "XNYS", "date": "2019-10-10T00:00:00+0000"}, {"open": 25.75, "high": 25.75, "low": 25.68, "close": 25.69, "volume": 31901.0, "adj_high": null, "adj_low": null, "adj_close": 24.7236, "adj_open": null, "adj_volume": null, "symbol": "CIM/PD", "exchange": "XNYS", "date": "2019-10-11T00:00:00+0000"}, {"open": 25.7, "high": 25.75, "low": 25.65, "close": 25.65, "volume": 42074.0, "adj_high": null, "adj_low": null, "adj_close": 24.6851, "adj_open": null, "adj_volume": null, "symbol": "CIM/PD", "exchange": "XNYS", "date": "2019-10-14T00:00:00+0000"}, {"open": 25.72, "high": 25.72, "low": 25.665, "close": 25.688, "volume": 53740.0, "adj_high": null, "adj_low": null, "adj_close": 24.7217, "adj_open": null, "adj_volume": null, "symbol": "CIM/PD", "exchange": "XNYS", "date": "2019-10-15T00:00:00+0000"}, {"open": 25.69, "high": 25.69, "low": 25.59, "close": 25.62, "volume": 79117.0, "adj_high": null, "adj_low": null, "adj_close": 24.6562, "adj_open": null, "adj_volume": null, "symbol": "CIM/PD", "exchange": "XNYS", "date": "2019-10-16T00:00:00+0000"}, {"open": 25.65, "high": 25.73, "low": 25.59, "close": 25.62, "volume": 84394.0, "adj_high": null, "adj_low": null, "adj_close": 24.6562, "adj_open": null, "adj_volume": null, "symbol": "CIM/PD", "exchange": "XNYS", "date": "2019-10-17T00:00:00+0000"}, {"open": 25.64, "high": 25.65, "low": 25.57, "close": 25.65, "volume": 55667.0, "adj_high": null, "adj_low": null, "adj_close": 24.6851, "adj_open": null, "adj_volume": null, "symbol": "CIM/PD", "exchange": "XNYS", "date": "2019-10-18T00:00:00+0000"}, {"open": 25.65, "high": 25.76, "low": 25.65, "close": 25.7, "volume": 14033.0, "adj_high": null, "adj_low": null, "adj_close": 24.7332, "adj_open": null, "adj_volume": null, "symbol": "CIM/PD", "exchange": "XNYS", "date": "2019-10-21T00:00:00+0000"}, {"open": 25.75, "high": 25.8, "low": 25.7497, "close": 25.78, "volume": 6388.0, "adj_high": null, "adj_low": null, "adj_close": 24.8102, "adj_open": null, "adj_volume": null, "symbol": "CIM/PD", "exchange": "XNYS", "date": "2019-10-22T00:00:00+0000"}, {"open": 25.8165, "high": 25.93, "low": 25.8, "close": 25.92, "volume": 12640.0, "adj_high": null, "adj_low": null, "adj_close": 24.9449, "adj_open": null, "adj_volume": null, "symbol": "CIM/PD", "exchange": "XNYS", "date": "2019-10-23T00:00:00+0000"}, {"open": 25.92, "high": 25.96, "low": 25.9, "close": 25.95, "volume": 13993.0, "adj_high": null, "adj_low": null, "adj_close": 24.9738, "adj_open": null, "adj_volume": null, "symbol": "CIM/PD", "exchange": "XNYS", "date": "2019-10-24T00:00:00+0000"}, {"open": 25.96, "high": 26.01, "low": 25.897, "close": 25.897, "volume": 10531.0, "adj_high": null, "adj_low": null, "adj_close": 24.9228, "adj_open": null, "adj_volume": null, "symbol": "CIM/PD", "exchange": "XNYS", "date": "2019-10-25T00:00:00+0000"}, {"open": 25.98, "high": 25.99, "low": 25.86, "close": 25.918, "volume": 16599.0, "adj_high": null, "adj_low": null, "adj_close": 24.943, "adj_open": null, "adj_volume": null, "symbol": "CIM/PD", "exchange": "XNYS", "date": "2019-10-28T00:00:00+0000"}, {"open": 25.9221, "high": 25.93, "low": 25.7812, "close": 25.8, "volume": 9344.0, "adj_high": null, "adj_low": null, "adj_close": 24.8294, "adj_open": null, "adj_volume": null, "symbol": "CIM/PD", "exchange": "XNYS", "date": "2019-10-29T00:00:00+0000"}, {"open": 25.8083, "high": 25.9, "low": 25.8083, "close": 25.84, "volume": 10139.0, "adj_high": null, "adj_low": null, "adj_close": 24.8679, "adj_open": null, "adj_volume": null, "symbol": "CIM/PD", "exchange": "XNYS", "date": "2019-10-30T00:00:00+0000"}, {"open": 25.88, "high": 25.91, "low": 25.74, "close": 25.74, "volume": 88680.0, "adj_high": null, "adj_low": null, "adj_close": 24.7717, "adj_open": null, "adj_volume": null, "symbol": "CIM/PD", "exchange": "XNYS", "date": "2019-10-31T00:00:00+0000"}, {"open": 25.8, "high": 25.91, "low": 25.8, "close": 25.91, "volume": 18886.0, "adj_high": null, "adj_low": null, "adj_close": 24.9353, "adj_open": null, "adj_volume": null, "symbol": "CIM/PD", "exchange": "XNYS", "date": "2019-11-01T00:00:00+0000"}, {"open": 25.94, "high": 26.2, "low": 25.914, "close": 26.1705, "volume": 126848.0, "adj_high": null, "adj_low": null, "adj_close": 25.186, "adj_open": null, "adj_volume": null, "symbol": "CIM/PD", "exchange": "XNYS", "date": "2019-11-04T00:00:00+0000"}, {"open": 26.21, "high": 26.2299, "low": 26.15, "close": 26.18, "volume": 34718.0, "adj_high": null, "adj_low": null, "adj_close": 25.1951, "adj_open": null, "adj_volume": null, "symbol": "CIM/PD", "exchange": "XNYS", "date": "2019-11-05T00:00:00+0000"}, {"open": 26.22, "high": 26.23, "low": 26.15, "close": 26.15, "volume": 14482.0, "adj_high": null, "adj_low": null, "adj_close": 25.1663, "adj_open": null, "adj_volume": null, "symbol": "CIM/PD", "exchange": "XNYS", "date": "2019-11-06T00:00:00+0000"}, {"open": 26.2119, "high": 26.2119, "low": 26.03, "close": 26.14, "volume": 29055.0, "adj_high": null, "adj_low": null, "adj_close": 25.1566, "adj_open": null, "adj_volume": null, "symbol": "CIM/PD", "exchange": "XNYS", "date": "2019-11-07T00:00:00+0000"}, {"open": 26.17, "high": 26.28, "low": 26.17, "close": 26.26, "volume": 24227.0, "adj_high": null, "adj_low": null, "adj_close": 25.2721, "adj_open": null, "adj_volume": null, "symbol": "CIM/PD", "exchange": "XNYS", "date": "2019-11-08T00:00:00+0000"}, {"open": 26.28, "high": 26.45, "low": 26.26, "close": 26.414, "volume": 61114.0, "adj_high": null, "adj_low": null, "adj_close": 25.4203, "adj_open": null, "adj_volume": null, "symbol": "CIM/PD", "exchange": "XNYS", "date": "2019-11-11T00:00:00+0000"}, {"open": 26.4354, "high": 26.5318, "low": 26.41, "close": 26.53, "volume": 40421.0, "adj_high": null, "adj_low": null, "adj_close": 25.532, "adj_open": null, "adj_volume": null, "symbol": "CIM/PD", "exchange": "XNYS", "date": "2019-11-12T00:00:00+0000"}, {"open": 26.54, "high": 26.61, "low": 26.53, "close": 26.5827, "volume": 19917.0, "adj_high": null, "adj_low": null, "adj_close": 25.5827, "adj_open": null, "adj_volume": null, "symbol": "CIM/PD", "exchange": "XNYS", "date": "2019-11-13T00:00:00+0000"}, {"open": 26.64, "high": 26.7, "low": 26.55, "close": 26.5999, "volume": 52894.0, "adj_high": null, "adj_low": null, "adj_close": 25.5992, "adj_open": null, "adj_volume": null, "symbol": "CIM/PD", "exchange": "XNYS", "date": "2019-11-14T00:00:00+0000"}, {"open": 26.67, "high": 26.67, "low": 26.53, "close": 26.53, "volume": 35916.0, "adj_high": null, "adj_low": null, "adj_close": 25.532, "adj_open": null, "adj_volume": null, "symbol": "CIM/PD", "exchange": "XNYS", "date": "2019-11-15T00:00:00+0000"}, {"open": 26.6, "high": 26.6, "low": 26.5, "close": 26.57, "volume": 12698.0, "adj_high": null, "adj_low": null, "adj_close": 25.5705, "adj_open": null, "adj_volume": null, "symbol": "CIM/PD", "exchange": "XNYS", "date": "2019-11-18T00:00:00+0000"}, {"open": 26.6108, "high": 26.62, "low": 26.51, "close": 26.62, "volume": 28212.0, "adj_high": null, "adj_low": null, "adj_close": 25.6186, "adj_open": null, "adj_volume": null, "symbol": "CIM/PD", "exchange": "XNYS", "date": "2019-11-19T00:00:00+0000"}, {"open": 26.6, "high": 26.6, "low": 26.4942, "close": 26.59, "volume": 17958.0, "adj_high": null, "adj_low": null, "adj_close": 25.5897, "adj_open": null, "adj_volume": null, "symbol": "CIM/PD", "exchange": "XNYS", "date": "2019-11-20T00:00:00+0000"}, {"open": 26.5, "high": 26.568, "low": 26.49, "close": 26.5645, "volume": 19662.0, "adj_high": null, "adj_low": null, "adj_close": 25.5652, "adj_open": null, "adj_volume": null, "symbol": "CIM/PD", "exchange": "XNYS", "date": "2019-11-21T00:00:00+0000"}, {"open": 26.52, "high": 26.6, "low": 26.44, "close": 26.6, "volume": 13259.0, "adj_high": null, "adj_low": null, "adj_close": 25.5993, "adj_open": null, "adj_volume": null, "symbol": "CIM/PD", "exchange": "XNYS", "date": "2019-11-22T00:00:00+0000"}, {"open": 26.4724, "high": 26.63, "low": 26.4724, "close": 26.63, "volume": 21558.0, "adj_high": null, "adj_low": null, "adj_close": 25.6282, "adj_open": null, "adj_volume": null, "symbol": "CIM/PD", "exchange": "XNYS", "date": "2019-11-25T00:00:00+0000"}, {"open": 26.6, "high": 26.69, "low": 26.5625, "close": 26.69, "volume": 27792.0, "adj_high": null, "adj_low": null, "adj_close": 25.686, "adj_open": null, "adj_volume": null, "symbol": "CIM/PD", "exchange": "XNYS", "date": "2019-11-26T00:00:00+0000"}, {"open": 26.3, "high": 26.325, "low": 26.19, "close": 26.19, "volume": 26481.0, "adj_high": null, "adj_low": null, "adj_close": 25.686, "adj_open": null, "adj_volume": null, "symbol": "CIM/PD", "exchange": "XNYS", "date": "2019-11-27T00:00:00+0000"}, {"open": 26.1406, "high": 26.19, "low": 26.03, "close": 26.03, "volume": 24786.0, "adj_high": null, "adj_low": null, "adj_close": 25.529, "adj_open": null, "adj_volume": null, "symbol": "CIM/PD", "exchange": "XNYS", "date": "2019-11-29T00:00:00+0000"}, {"open": 26.0301, "high": 26.047, "low": 26.0, "close": 26.0, "volume": 90644.0, "adj_high": null, "adj_low": null, "adj_close": 25.4996, "adj_open": null, "adj_volume": null, "symbol": "CIM/PD", "exchange": "XNYS", "date": "2019-12-02T00:00:00+0000"}, {"open": 26.0, "high": 26.024, "low": 25.92, "close": 26.02, "volume": 37231.0, "adj_high": null, "adj_low": null, "adj_close": 25.5192, "adj_open": null, "adj_volume": null, "symbol": "CIM/PD", "exchange": "XNYS", "date": "2019-12-03T00:00:00+0000"}, {"open": 26.1, "high": 26.14, "low": 25.98, "close": 25.98, "volume": 11084.0, "adj_high": null, "adj_low": null, "adj_close": 25.48, "adj_open": null, "adj_volume": null, "symbol": "CIM/PD", "exchange": "XNYS", "date": "2019-12-04T00:00:00+0000"}, {"open": 26.09, "high": 26.09, "low": 25.76, "close": 25.83, "volume": 38755.0, "adj_high": null, "adj_low": null, "adj_close": 25.3329, "adj_open": null, "adj_volume": null, "symbol": "CIM/PD", "exchange": "XNYS", "date": "2019-12-05T00:00:00+0000"}, {"open": 25.77, "high": 25.96, "low": 25.77, "close": 25.92, "volume": 11685.0, "adj_high": null, "adj_low": null, "adj_close": 25.4212, "adj_open": null, "adj_volume": null, "symbol": "CIM/PD", "exchange": "XNYS", "date": "2019-12-06T00:00:00+0000"}, {"open": 25.9445, "high": 26.1142, "low": 25.92, "close": 25.92, "volume": 9743.0, "adj_high": null, "adj_low": null, "adj_close": 25.4212, "adj_open": null, "adj_volume": null, "symbol": "CIM/PD", "exchange": "XNYS", "date": "2019-12-09T00:00:00+0000"}, {"open": 25.9, "high": 26.0825, "low": 25.9, "close": 25.95, "volume": 16795.0, "adj_high": null, "adj_low": null, "adj_close": 25.4506, "adj_open": null, "adj_volume": null, "symbol": "CIM/PD", "exchange": "XNYS", "date": "2019-12-10T00:00:00+0000"}, {"open": 25.97, "high": 26.0, "low": 25.96, "close": 26.0, "volume": 4614.0, "adj_high": null, "adj_low": null, "adj_close": 25.4996, "adj_open": null, "adj_volume": null, "symbol": "CIM/PD", "exchange": "XNYS", "date": "2019-12-11T00:00:00+0000"}, {"open": 26.01, "high": 26.11, "low": 25.96, "close": 25.9989, "volume": 36597.0, "adj_high": null, "adj_low": null, "adj_close": 25.4985, "adj_open": null, "adj_volume": null, "symbol": "CIM/PD", "exchange": "XNYS", "date": "2019-12-12T00:00:00+0000"}, {"open": 26.0, "high": 26.1793, "low": 26.0, "close": 26.1563, "volume": 5339.0, "adj_high": null, "adj_low": null, "adj_close": 25.6529, "adj_open": null, "adj_volume": null, "symbol": "CIM/PD", "exchange": "XNYS", "date": "2019-12-13T00:00:00+0000"}, {"open": 26.1488, "high": 26.16, "low": 26.1, "close": 26.16, "volume": 7422.0, "adj_high": null, "adj_low": null, "adj_close": 25.6565, "adj_open": null, "adj_volume": null, "symbol": "CIM/PD", "exchange": "XNYS", "date": "2019-12-16T00:00:00+0000"}, {"open": 26.25, "high": 26.34, "low": 26.1396, "close": 26.34, "volume": 7464.0, "adj_high": null, "adj_low": null, "adj_close": 25.8331, "adj_open": null, "adj_volume": null, "symbol": "CIM/PD", "exchange": "XNYS", "date": "2019-12-17T00:00:00+0000"}, {"open": 26.34, "high": 26.38, "low": 26.2, "close": 26.38, "volume": 6167.0, "adj_high": null, "adj_low": null, "adj_close": 25.8723, "adj_open": null, "adj_volume": null, "symbol": "CIM/PD", "exchange": "XNYS", "date": "2019-12-18T00:00:00+0000"}, {"open": 26.23, "high": 26.37, "low": 26.23, "close": 26.35, "volume": 11410.0, "adj_high": null, "adj_low": null, "adj_close": 25.8429, "adj_open": null, "adj_volume": null, "symbol": "CIM/PD", "exchange": "XNYS", "date": "2019-12-19T00:00:00+0000"}, {"open": 26.322, "high": 26.3925, "low": 26.322, "close": 26.35, "volume": 2125.0, "adj_high": null, "adj_low": null, "adj_close": 25.8429, "adj_open": null, "adj_volume": null, "symbol": "CIM/PD", "exchange": "XNYS", "date": "2019-12-20T00:00:00+0000"}, {"open": 26.38, "high": 26.39, "low": 26.2707, "close": 26.3133, "volume": 2942.0, "adj_high": null, "adj_low": null, "adj_close": 25.8069, "adj_open": null, "adj_volume": null, "symbol": "CIM/PD", "exchange": "XNYS", "date": "2019-12-23T00:00:00+0000"}, {"open": 26.3095, "high": 26.33, "low": 26.3095, "close": 26.32, "volume": 1823.0, "adj_high": null, "adj_low": null, "adj_close": 25.8135, "adj_open": null, "adj_volume": null, "symbol": "CIM/PD", "exchange": "XNYS", "date": "2019-12-24T00:00:00+0000"}, {"open": 26.2983, "high": 26.2983, "low": 26.12, "close": 26.2751, "volume": 19084.0, "adj_high": null, "adj_low": null, "adj_close": 25.7694, "adj_open": null, "adj_volume": null, "symbol": "CIM/PD", "exchange": "XNYS", "date": "2019-12-26T00:00:00+0000"}, {"open": 26.25, "high": 26.2962, "low": 26.25, "close": 26.275, "volume": 4617.0, "adj_high": null, "adj_low": null, "adj_close": 25.7693, "adj_open": null, "adj_volume": null, "symbol": "CIM/PD", "exchange": "XNYS", "date": "2019-12-27T00:00:00+0000"}, {"open": 26.26, "high": 26.27, "low": 26.25, "close": 26.2591, "volume": 6293.0, "adj_high": null, "adj_low": null, "adj_close": 25.7537, "adj_open": null, "adj_volume": null, "symbol": "CIM/PD", "exchange": "XNYS", "date": "2019-12-30T00:00:00+0000"}, {"open": 26.2975, "high": 26.32, "low": 26.27, "close": 26.32, "volume": 5372.0, "adj_high": null, "adj_low": null, "adj_close": 25.8135, "adj_open": null, "adj_volume": null, "symbol": "CIM/PD", "exchange": "XNYS", "date": "2019-12-31T00:00:00+0000"}, {"open": 26.25, "high": 26.5831, "low": 26.25, "close": 26.52, "volume": 17346.0, "adj_high": null, "adj_low": null, "adj_close": 26.0096, "adj_open": null, "adj_volume": null, "symbol": "CIM/PD", "exchange": "XNYS", "date": "2020-01-02T00:00:00+0000"}, {"open": 26.54, "high": 26.59, "low": 26.4511, "close": 26.53, "volume": 7148.0, "adj_high": null, "adj_low": null, "adj_close": 26.0194, "adj_open": null, "adj_volume": null, "symbol": "CIM/PD", "exchange": "XNYS", "date": "2020-01-03T00:00:00+0000"}, {"open": 26.54, "high": 26.54, "low": 26.411, "close": 26.5, "volume": 7958.0, "adj_high": null, "adj_low": null, "adj_close": 25.99, "adj_open": null, "adj_volume": null, "symbol": "CIM/PD", "exchange": "XNYS", "date": "2020-01-06T00:00:00+0000"}, {"open": 26.5484, "high": 26.5484, "low": 26.28, "close": 26.28, "volume": 13585.0, "adj_high": null, "adj_low": null, "adj_close": 25.7742, "adj_open": null, "adj_volume": null, "symbol": "CIM/PD", "exchange": "XNYS", "date": "2020-01-07T00:00:00+0000"}, {"open": 26.26, "high": 26.505, "low": 26.26, "close": 26.34, "volume": 16380.0, "adj_high": null, "adj_low": null, "adj_close": 25.8331, "adj_open": null, "adj_volume": null, "symbol": "CIM/PD", "exchange": "XNYS", "date": "2020-01-08T00:00:00+0000"}, {"open": 26.45, "high": 26.45, "low": 26.3344, "close": 26.37, "volume": 4637.0, "adj_high": null, "adj_low": null, "adj_close": 25.8625, "adj_open": null, "adj_volume": null, "symbol": "CIM/PD", "exchange": "XNYS", "date": "2020-01-09T00:00:00+0000"}, {"open": 26.34, "high": 26.492, "low": 26.33, "close": 26.46, "volume": 5837.0, "adj_high": null, "adj_low": null, "adj_close": 25.9508, "adj_open": null, "adj_volume": null, "symbol": "CIM/PD", "exchange": "XNYS", "date": "2020-01-10T00:00:00+0000"}, {"open": 26.4552, "high": 26.55, "low": 26.4552, "close": 26.55, "volume": 6296.0, "adj_high": null, "adj_low": null, "adj_close": 26.039, "adj_open": null, "adj_volume": null, "symbol": "CIM/PD", "exchange": "XNYS", "date": "2020-01-13T00:00:00+0000"}, {"open": 26.57, "high": 26.5888, "low": 26.56, "close": 26.575, "volume": 4080.0, "adj_high": null, "adj_low": null, "adj_close": 26.0635, "adj_open": null, "adj_volume": null, "symbol": "CIM/PD", "exchange": "XNYS", "date": "2020-01-14T00:00:00+0000"}, {"open": 26.5, "high": 26.56, "low": 26.5, "close": 26.52, "volume": 9521.0, "adj_high": null, "adj_low": null, "adj_close": 26.0096, "adj_open": null, "adj_volume": null, "symbol": "CIM/PD", "exchange": "XNYS", "date": "2020-01-15T00:00:00+0000"}, {"open": 26.497, "high": 26.497, "low": 26.47, "close": 26.47, "volume": 25305.0, "adj_high": null, "adj_low": null, "adj_close": 25.9606, "adj_open": null, "adj_volume": null, "symbol": "CIM/PD", "exchange": "XNYS", "date": "2020-01-16T00:00:00+0000"}, {"open": 26.45, "high": 26.6, "low": 26.25, "close": 26.42, "volume": 20561.0, "adj_high": null, "adj_low": null, "adj_close": 25.9115, "adj_open": null, "adj_volume": null, "symbol": "CIM/PD", "exchange": "XNYS", "date": "2020-01-17T00:00:00+0000"}, {"open": 26.42, "high": 26.62, "low": 26.356, "close": 26.55, "volume": 29003.0, "adj_high": null, "adj_low": null, "adj_close": 26.039, "adj_open": null, "adj_volume": null, "symbol": "CIM/PD", "exchange": "XNYS", "date": "2020-01-21T00:00:00+0000"}, {"open": 26.5, "high": 26.5, "low": 26.48, "close": 26.5, "volume": 5972.0, "adj_high": null, "adj_low": null, "adj_close": 25.99, "adj_open": null, "adj_volume": null, "symbol": "CIM/PD", "exchange": "XNYS", "date": "2020-01-22T00:00:00+0000"}, {"open": 26.5, "high": 26.5, "low": 26.43, "close": 26.43, "volume": 10233.0, "adj_high": null, "adj_low": null, "adj_close": 25.9213, "adj_open": null, "adj_volume": null, "symbol": "CIM/PD", "exchange": "XNYS", "date": "2020-01-23T00:00:00+0000"}, {"open": 26.5, "high": 26.5, "low": 26.27, "close": 26.47, "volume": 28138.0, "adj_high": null, "adj_low": null, "adj_close": 25.9606, "adj_open": null, "adj_volume": null, "symbol": "CIM/PD", "exchange": "XNYS", "date": "2020-01-24T00:00:00+0000"}, {"open": 26.41, "high": 26.41, "low": 26.22, "close": 26.3909, "volume": 15326.0, "adj_high": null, "adj_low": null, "adj_close": 25.883, "adj_open": null, "adj_volume": null, "symbol": "CIM/PD", "exchange": "XNYS", "date": "2020-01-27T00:00:00+0000"}, {"open": 26.42, "high": 26.445, "low": 26.29, "close": 26.34, "volume": 22535.0, "adj_high": null, "adj_low": null, "adj_close": 25.8331, "adj_open": null, "adj_volume": null, "symbol": "CIM/PD", "exchange": "XNYS", "date": "2020-01-28T00:00:00+0000"}, {"open": 26.4092, "high": 26.5325, "low": 26.35, "close": 26.5325, "volume": 22269.0, "adj_high": null, "adj_low": null, "adj_close": 26.0219, "adj_open": null, "adj_volume": null, "symbol": "CIM/PD", "exchange": "XNYS", "date": "2020-01-29T00:00:00+0000"}, {"open": 26.45, "high": 26.6, "low": 26.45, "close": 26.5943, "volume": 11973.0, "adj_high": null, "adj_low": null, "adj_close": 26.0825, "adj_open": null, "adj_volume": null, "symbol": "CIM/PD", "exchange": "XNYS", "date": "2020-01-30T00:00:00+0000"}, {"open": 26.64, "high": 26.7, "low": 26.48, "close": 26.65, "volume": 17791.0, "adj_high": null, "adj_low": null, "adj_close": 26.1371, "adj_open": null, "adj_volume": null, "symbol": "CIM/PD", "exchange": "XNYS", "date": "2020-01-31T00:00:00+0000"}, {"open": 26.55, "high": 26.87, "low": 26.43, "close": 26.7506, "volume": 29195.0, "adj_high": null, "adj_low": null, "adj_close": 26.2358, "adj_open": null, "adj_volume": null, "symbol": "CIM/PD", "exchange": "XNYS", "date": "2020-02-03T00:00:00+0000"}, {"open": 26.7, "high": 26.82, "low": 26.6, "close": 26.6037, "volume": 15713.0, "adj_high": null, "adj_low": null, "adj_close": 26.0917, "adj_open": null, "adj_volume": null, "symbol": "CIM/PD", "exchange": "XNYS", "date": "2020-02-04T00:00:00+0000"}, {"open": 26.675, "high": 26.77, "low": 26.675, "close": 26.7322, "volume": 14355.0, "adj_high": null, "adj_low": null, "adj_close": 26.2177, "adj_open": null, "adj_volume": null, "symbol": "CIM/PD", "exchange": "XNYS", "date": "2020-02-05T00:00:00+0000"}, {"open": 26.62, "high": 26.75, "low": 26.57, "close": 26.7259, "volume": 12386.0, "adj_high": null, "adj_low": null, "adj_close": 26.2115, "adj_open": null, "adj_volume": null, "symbol": "CIM/PD", "exchange": "XNYS", "date": "2020-02-06T00:00:00+0000"}, {"open": 26.7192, "high": 26.74, "low": 26.62, "close": 26.6698, "volume": 8469.0, "adj_high": null, "adj_low": null, "adj_close": 26.1565, "adj_open": null, "adj_volume": null, "symbol": "CIM/PD", "exchange": "XNYS", "date": "2020-02-07T00:00:00+0000"}, {"open": 26.67, "high": 26.75, "low": 26.64, "close": 26.64, "volume": 9140.0, "adj_high": null, "adj_low": null, "adj_close": 26.1273, "adj_open": null, "adj_volume": null, "symbol": "CIM/PD", "exchange": "XNYS", "date": "2020-02-10T00:00:00+0000"}, {"open": 26.72, "high": 26.72, "low": 26.58, "close": 26.58, "volume": 12981.0, "adj_high": null, "adj_low": null, "adj_close": 26.0685, "adj_open": null, "adj_volume": null, "symbol": "CIM/PD", "exchange": "XNYS", "date": "2020-02-11T00:00:00+0000"}, {"open": 26.7, "high": 26.72, "low": 26.58, "close": 26.6, "volume": 18125.0, "adj_high": null, "adj_low": null, "adj_close": 26.0881, "adj_open": null, "adj_volume": null, "symbol": "CIM/PD", "exchange": "XNYS", "date": "2020-02-12T00:00:00+0000"}, {"open": 26.62, "high": 26.69, "low": 26.62, "close": 26.68, "volume": 4134.0, "adj_high": null, "adj_low": null, "adj_close": 26.1665, "adj_open": null, "adj_volume": null, "symbol": "CIM/PD", "exchange": "XNYS", "date": "2020-02-13T00:00:00+0000"}, {"open": 26.68, "high": 26.68, "low": 26.65, "close": 26.654, "volume": 25925.0, "adj_high": null, "adj_low": null, "adj_close": 26.141, "adj_open": null, "adj_volume": null, "symbol": "CIM/PD", "exchange": "XNYS", "date": "2020-02-14T00:00:00+0000"}, {"open": 26.64, "high": 26.64, "low": 26.58, "close": 26.63, "volume": 17599.0, "adj_high": null, "adj_low": null, "adj_close": 26.1175, "adj_open": null, "adj_volume": null, "symbol": "CIM/PD", "exchange": "XNYS", "date": "2020-02-18T00:00:00+0000"}, {"open": 26.55, "high": 26.62, "low": 26.55, "close": 26.57, "volume": 33662.0, "adj_high": null, "adj_low": null, "adj_close": 26.0586, "adj_open": null, "adj_volume": null, "symbol": "CIM/PD", "exchange": "XNYS", "date": "2020-02-19T00:00:00+0000"}, {"open": 26.56, "high": 26.6899, "low": 26.53, "close": 26.6804, "volume": 19676.0, "adj_high": null, "adj_low": null, "adj_close": 26.1669, "adj_open": null, "adj_volume": null, "symbol": "CIM/PD", "exchange": "XNYS", "date": "2020-02-20T00:00:00+0000"}, {"open": 26.646, "high": 26.69, "low": 26.55, "close": 26.55, "volume": 7846.0, "adj_high": null, "adj_low": null, "adj_close": 26.039, "adj_open": null, "adj_volume": null, "symbol": "CIM/PD", "exchange": "XNYS", "date": "2020-02-21T00:00:00+0000"}, {"open": 26.5, "high": 26.6399, "low": 26.33, "close": 26.33, "volume": 10788.0, "adj_high": null, "adj_low": null, "adj_close": 25.8233, "adj_open": null, "adj_volume": null, "symbol": "CIM/PD", "exchange": "XNYS", "date": "2020-02-24T00:00:00+0000"}, {"open": 26.52, "high": 26.5842, "low": 26.02, "close": 26.02, "volume": 43204.0, "adj_high": null, "adj_low": null, "adj_close": 25.5192, "adj_open": null, "adj_volume": null, "symbol": "CIM/PD", "exchange": "XNYS", "date": "2020-02-25T00:00:00+0000"}, {"open": 26.0, "high": 26.46, "low": 25.81, "close": 25.98, "volume": 91246.0, "adj_high": null, "adj_low": null, "adj_close": 25.48, "adj_open": null, "adj_volume": null, "symbol": "CIM/PD", "exchange": "XNYS", "date": "2020-02-26T00:00:00+0000"}, {"open": 25.37, "high": 26.19, "low": 25.02, "close": 25.8, "volume": 82083.0, "adj_high": null, "adj_low": null, "adj_close": 25.8, "adj_open": null, "adj_volume": null, "symbol": "CIM/PD", "exchange": "XNYS", "date": "2020-02-27T00:00:00+0000"}, {"open": 25.4836, "high": 25.5, "low": 24.8161, "close": 25.5, "volume": 123934.0, "adj_high": null, "adj_low": null, "adj_close": 25.5, "adj_open": null, "adj_volume": null, "symbol": "CIM/PD", "exchange": "XNYS", "date": "2020-02-28T00:00:00+0000"}, {"open": 25.25, "high": 25.99, "low": 25.2, "close": 25.7, "volume": 69442.0, "adj_high": null, "adj_low": null, "adj_close": 25.7, "adj_open": null, "adj_volume": null, "symbol": "CIM/PD", "exchange": "XNYS", "date": "2020-03-02T00:00:00+0000"}, {"open": 25.98, "high": 26.2903, "low": 25.81, "close": 26.118, "volume": 52994.0, "adj_high": null, "adj_low": null, "adj_close": 26.118, "adj_open": null, "adj_volume": null, "symbol": "CIM/PD", "exchange": "XNYS", "date": "2020-03-03T00:00:00+0000"}, {"open": 26.1, "high": 26.275, "low": 26.1, "close": 26.2393, "volume": 7447.0, "adj_high": null, "adj_low": null, "adj_close": 26.2393, "adj_open": null, "adj_volume": null, "symbol": "CIM/PD", "exchange": "XNYS", "date": "2020-03-04T00:00:00+0000"}, {"open": 26.24, "high": 26.2595, "low": 25.6, "close": 25.95, "volume": 120060.0, "adj_high": null, "adj_low": null, "adj_close": 25.95, "adj_open": null, "adj_volume": null, "symbol": "CIM/PD", "exchange": "XNYS", "date": "2020-03-05T00:00:00+0000"}, {"open": 25.5, "high": 25.8896, "low": 25.3, "close": 25.85, "volume": 36611.0, "adj_high": null, "adj_low": null, "adj_close": 25.85, "adj_open": null, "adj_volume": null, "symbol": "CIM/PD", "exchange": "XNYS", "date": "2020-03-06T00:00:00+0000"}, {"open": 25.01, "high": 25.06, "low": 23.28, "close": 24.5134, "volume": 65609.0, "adj_high": null, "adj_low": null, "adj_close": 24.5134, "adj_open": null, "adj_volume": null, "symbol": "CIM/PD", "exchange": "XNYS", "date": "2020-03-09T00:00:00+0000"}, {"open": 25.66, "high": 25.66, "low": 24.125, "close": 24.51, "volume": 39260.0, "adj_high": null, "adj_low": null, "adj_close": 24.51, "adj_open": null, "adj_volume": null, "symbol": "CIM/PD", "exchange": "XNYS", "date": "2020-03-10T00:00:00+0000"}, {"open": 24.17, "high": 24.43, "low": 23.51, "close": 23.51, "volume": 35458.0, "adj_high": null, "adj_low": null, "adj_close": 23.51, "adj_open": null, "adj_volume": null, "symbol": "CIM/PD", "exchange": "XNYS", "date": "2020-03-11T00:00:00+0000"}, {"open": 22.75, "high": 22.75, "low": 18.06, "close": 20.9, "volume": 155670.0, "adj_high": null, "adj_low": null, "adj_close": 20.9, "adj_open": null, "adj_volume": null, "symbol": "CIM/PD", "exchange": "XNYS", "date": "2020-03-12T00:00:00+0000"}, {"open": 21.07, "high": 21.6585, "low": 20.0, "close": 21.44, "volume": 63491.0, "adj_high": null, "adj_low": null, "adj_close": 21.44, "adj_open": null, "adj_volume": null, "symbol": "CIM/PD", "exchange": "XNYS", "date": "2020-03-13T00:00:00+0000"}, {"open": 19.25, "high": 19.8, "low": 18.15, "close": 18.35, "volume": 60067.0, "adj_high": null, "adj_low": null, "adj_close": 18.35, "adj_open": null, "adj_volume": null, "symbol": "CIM/PD", "exchange": "XNYS", "date": "2020-03-16T00:00:00+0000"}, {"open": 18.35, "high": 18.51, "low": 13.51, "close": 13.85, "volume": 102473.0, "adj_high": null, "adj_low": null, "adj_close": 13.85, "adj_open": null, "adj_volume": null, "symbol": "CIM/PD", "exchange": "XNYS", "date": "2020-03-17T00:00:00+0000"}, {"open": 13.5, "high": 13.5, "low": 6.83, "close": 11.19, "volume": 286839.0, "adj_high": null, "adj_low": null, "adj_close": 11.19, "adj_open": null, "adj_volume": null, "symbol": "CIM/PD", "exchange": "XNYS", "date": "2020-03-18T00:00:00+0000"}, {"open": 11.19, "high": 18.5, "low": 10.29, "close": 15.25, "volume": 128640.0, "adj_high": null, "adj_low": null, "adj_close": 15.25, "adj_open": null, "adj_volume": null, "symbol": "CIM/PD", "exchange": "XNYS", "date": "2020-03-19T00:00:00+0000"}, {"open": 15.25, "high": 16.4217, "low": 13.21, "close": 13.3, "volume": 218575.0, "adj_high": null, "adj_low": null, "adj_close": 13.3, "adj_open": null, "adj_volume": null, "symbol": "CIM/PD", "exchange": "XNYS", "date": "2020-03-20T00:00:00+0000"}, {"open": 12.75, "high": 12.75, "low": 7.04, "close": 8.5, "volume": 205098.0, "adj_high": null, "adj_low": null, "adj_close": 8.5, "adj_open": null, "adj_volume": null, "symbol": "CIM/PD", "exchange": "XNYS", "date": "2020-03-23T00:00:00+0000"}, {"open": 9.13, "high": 10.002, "low": 7.55, "close": 7.604, "volume": 240305.0, "adj_high": null, "adj_low": null, "adj_close": 7.604, "adj_open": null, "adj_volume": null, "symbol": "CIM/PD", "exchange": "XNYS", "date": "2020-03-24T00:00:00+0000"}, {"open": 8.36, "high": 10.3899, "low": 7.5, "close": 10.26, "volume": 624715.0, "adj_high": null, "adj_low": null, "adj_close": 10.26, "adj_open": null, "adj_volume": null, "symbol": "CIM/PD", "exchange": "XNYS", "date": "2020-03-25T00:00:00+0000"}, {"open": 11.12, "high": 15.4, "low": 11.12, "close": 15.18, "volume": 411346.0, "adj_high": null, "adj_low": null, "adj_close": 15.18, "adj_open": null, "adj_volume": null, "symbol": "CIM/PD", "exchange": "XNYS", "date": "2020-03-26T00:00:00+0000"}, {"open": 14.5, "high": 17.64, "low": 13.932, "close": 17.39, "volume": 383323.0, "adj_high": null, "adj_low": null, "adj_close": 17.39, "adj_open": null, "adj_volume": null, "symbol": "CIM/PD", "exchange": "XNYS", "date": "2020-03-27T00:00:00+0000"}, {"open": 16.39, "high": 16.39, "low": 14.51, "close": 14.85, "volume": 72729.0, "adj_high": null, "adj_low": null, "adj_close": 14.85, "adj_open": null, "adj_volume": null, "symbol": "CIM/PD", "exchange": "XNYS", "date": "2020-03-30T00:00:00+0000"}, {"open": 15.15, "high": 15.6, "low": 14.765, "close": 14.89, "volume": 148926.0, "adj_high": null, "adj_low": null, "adj_close": 14.89, "adj_open": null, "adj_volume": null, "symbol": "CIM/PD", "exchange": "XNYS", "date": "2020-03-31T00:00:00+0000"}, {"open": 13.39, "high": 13.99, "low": 12.53, "close": 13.015, "volume": 94529.0, "adj_high": null, "adj_low": null, "adj_close": 13.015, "adj_open": null, "adj_volume": null, "symbol": "CIM/PD", "exchange": "XNYS", "date": "2020-04-01T00:00:00+0000"}, {"open": 13.08, "high": 13.08, "low": 12.11, "close": 12.11, "volume": 59627.0, "adj_high": null, "adj_low": null, "adj_close": 12.11, "adj_open": null, "adj_volume": null, "symbol": "CIM/PD", "exchange": "XNYS", "date": "2020-04-02T00:00:00+0000"}, {"open": 12.1, "high": 12.1, "low": 9.94, "close": 10.78, "volume": 93265.0, "adj_high": null, "adj_low": null, "adj_close": 10.78, "adj_open": null, "adj_volume": null, "symbol": "CIM/PD", "exchange": "XNYS", "date": "2020-04-03T00:00:00+0000"}, {"open": 11.86, "high": 13.635, "low": 11.0, "close": 11.32, "volume": 62340.0, "adj_high": null, "adj_low": null, "adj_close": 11.32, "adj_open": null, "adj_volume": null, "symbol": "CIM/PD", "exchange": "XNYS", "date": "2020-04-06T00:00:00+0000"}, {"open": 12.54, "high": 16.202, "low": 12.54, "close": 15.32, "volume": 212937.0, "adj_high": null, "adj_low": null, "adj_close": 15.32, "adj_open": null, "adj_volume": null, "symbol": "CIM/PD", "exchange": "XNYS", "date": "2020-04-07T00:00:00+0000"}, {"open": 16.05, "high": 17.05, "low": 16.0, "close": 16.76, "volume": 72407.0, "adj_high": null, "adj_low": null, "adj_close": 16.76, "adj_open": null, "adj_volume": null, "symbol": "CIM/PD", "exchange": "XNYS", "date": "2020-04-08T00:00:00+0000"}, {"open": 17.25, "high": 19.3, "low": 17.15, "close": 17.5, "volume": 72689.0, "adj_high": null, "adj_low": null, "adj_close": 17.5, "adj_open": null, "adj_volume": null, "symbol": "CIM/PD", "exchange": "XNYS", "date": "2020-04-09T00:00:00+0000"}, {"open": 17.1955, "high": 17.5925, "low": 16.4534, "close": 17.29, "volume": 34190.0, "adj_high": null, "adj_low": null, "adj_close": 17.29, "adj_open": null, "adj_volume": null, "symbol": "CIM/PD", "exchange": "XNYS", "date": "2020-04-13T00:00:00+0000"}, {"open": 18.016, "high": 18.36, "low": 17.0, "close": 17.0445, "volume": 20466.0, "adj_high": null, "adj_low": null, "adj_close": 17.0445, "adj_open": null, "adj_volume": null, "symbol": "CIM/PD", "exchange": "XNYS", "date": "2020-04-14T00:00:00+0000"}, {"open": 15.66, "high": 16.6499, "low": 15.5001, "close": 16.0, "volume": 88183.0, "adj_high": null, "adj_low": null, "adj_close": 16.0, "adj_open": null, "adj_volume": null, "symbol": "CIM/PD", "exchange": "XNYS", "date": "2020-04-15T00:00:00+0000"}, {"open": 16.0, "high": 16.15, "low": 15.31, "close": 16.0, "volume": 90892.0, "adj_high": null, "adj_low": null, "adj_close": 16.0, "adj_open": null, "adj_volume": null, "symbol": "CIM/PD", "exchange": "XNYS", "date": "2020-04-16T00:00:00+0000"}, {"open": 16.5, "high": 16.6255, "low": 16.08, "close": 16.46, "volume": 75717.0, "adj_high": null, "adj_low": null, "adj_close": 16.46, "adj_open": null, "adj_volume": null, "symbol": "CIM/PD", "exchange": "XNYS", "date": "2020-04-17T00:00:00+0000"}, {"open": 16.0, "high": 16.25, "low": 15.65, "close": 15.82, "volume": 141058.0, "adj_high": null, "adj_low": null, "adj_close": 15.82, "adj_open": null, "adj_volume": null, "symbol": "CIM/PD", "exchange": "XNYS", "date": "2020-04-20T00:00:00+0000"}, {"open": 15.97, "high": 16.29, "low": 15.5, "close": 16.25, "volume": 134482.0, "adj_high": null, "adj_low": null, "adj_close": 16.25, "adj_open": null, "adj_volume": null, "symbol": "CIM/PD", "exchange": "XNYS", "date": "2020-04-21T00:00:00+0000"}, {"open": 16.5, "high": 17.0, "low": 16.26, "close": 16.4, "volume": 82068.0, "adj_high": null, "adj_low": null, "adj_close": 16.4, "adj_open": null, "adj_volume": null, "symbol": "CIM/PD", "exchange": "XNYS", "date": "2020-04-22T00:00:00+0000"}, {"open": 16.4, "high": 16.6, "low": 16.17, "close": 16.52, "volume": 61800.0, "adj_high": null, "adj_low": null, "adj_close": 16.52, "adj_open": null, "adj_volume": null, "symbol": "CIM/PD", "exchange": "XNYS", "date": "2020-04-23T00:00:00+0000"}, {"open": 16.58, "high": 16.645, "low": 16.03, "close": 16.52, "volume": 61435.0, "adj_high": null, "adj_low": null, "adj_close": 16.52, "adj_open": null, "adj_volume": null, "symbol": "CIM/PD", "exchange": "XNYS", "date": "2020-04-24T00:00:00+0000"}, {"open": 16.65, "high": 16.7, "low": 16.17, "close": 16.4, "volume": 151541.0, "adj_high": null, "adj_low": null, "adj_close": 16.4, "adj_open": null, "adj_volume": null, "symbol": "CIM/PD", "exchange": "XNYS", "date": "2020-04-27T00:00:00+0000"}, {"open": 16.65, "high": 17.34, "low": 16.575, "close": 16.8, "volume": 111788.0, "adj_high": null, "adj_low": null, "adj_close": 16.8, "adj_open": null, "adj_volume": null, "symbol": "CIM/PD", "exchange": "XNYS", "date": "2020-04-28T00:00:00+0000"}, {"open": 16.98, "high": 17.96, "low": 16.98, "close": 17.72, "volume": 38246.0, "adj_high": null, "adj_low": null, "adj_close": 17.72, "adj_open": null, "adj_volume": null, "symbol": "CIM/PD", "exchange": "XNYS", "date": "2020-04-29T00:00:00+0000"}, {"open": 17.8, "high": 18.2, "low": 17.23, "close": 17.61, "volume": 60222.0, "adj_high": null, "adj_low": null, "adj_close": 17.61, "adj_open": null, "adj_volume": null, "symbol": "CIM/PD", "exchange": "XNYS", "date": "2020-04-30T00:00:00+0000"}, {"open": 17.75, "high": 17.8388, "low": 17.04, "close": 17.3325, "volume": 40201.0, "adj_high": null, "adj_low": null, "adj_close": 17.3325, "adj_open": null, "adj_volume": null, "symbol": "CIM/PD", "exchange": "XNYS", "date": "2020-05-01T00:00:00+0000"}, {"open": 17.305, "high": 17.4499, "low": 17.0, "close": 17.215, "volume": 33759.0, "adj_high": null, "adj_low": null, "adj_close": 17.215, "adj_open": null, "adj_volume": null, "symbol": "CIM/PD", "exchange": "XNYS", "date": "2020-05-04T00:00:00+0000"}, {"open": 17.4, "high": 18.098, "low": 17.4, "close": 17.92, "volume": 38563.0, "adj_high": null, "adj_low": null, "adj_close": 17.92, "adj_open": null, "adj_volume": null, "symbol": "CIM/PD", "exchange": "XNYS", "date": "2020-05-05T00:00:00+0000"}, {"open": 18.0, "high": 18.1, "low": 17.9, "close": 18.05, "volume": 54903.0, "adj_high": null, "adj_low": null, "adj_close": 18.05, "adj_open": null, "adj_volume": null, "symbol": "CIM/PD", "exchange": "XNYS", "date": "2020-05-06T00:00:00+0000"}, {"open": 18.25, "high": 18.25, "low": 17.85, "close": 18.08, "volume": 38401.0, "adj_high": null, "adj_low": null, "adj_close": 18.08, "adj_open": null, "adj_volume": null, "symbol": "CIM/PD", "exchange": "XNYS", "date": "2020-05-07T00:00:00+0000"}, {"open": 18.32, "high": 18.5, "low": 17.9999, "close": 18.3, "volume": 39674.0, "adj_high": null, "adj_low": null, "adj_close": 18.3, "adj_open": null, "adj_volume": null, "symbol": "CIM/PD", "exchange": "XNYS", "date": "2020-05-08T00:00:00+0000"}, {"open": 19.14, "high": 19.14, "low": 18.01, "close": 18.13, "volume": 28082.0, "adj_high": null, "adj_low": null, "adj_close": 18.13, "adj_open": null, "adj_volume": null, "symbol": "CIM/PD", "exchange": "XNYS", "date": "2020-05-11T00:00:00+0000"}, {"open": 18.2, "high": 18.35, "low": 17.58, "close": 17.8, "volume": 162676.0, "adj_high": null, "adj_low": null, "adj_close": 17.8, "adj_open": null, "adj_volume": null, "symbol": "CIM/PD", "exchange": "XNYS", "date": "2020-05-12T00:00:00+0000"}, {"open": 17.9, "high": 17.9, "low": 17.0, "close": 17.1, "volume": 41259.0, "adj_high": null, "adj_low": null, "adj_close": 17.1, "adj_open": null, "adj_volume": null, "symbol": "CIM/PD", "exchange": "XNYS", "date": "2020-05-13T00:00:00+0000"}, {"open": 17.1, "high": 17.1, "low": 16.01, "close": 16.7002, "volume": 50869.0, "adj_high": null, "adj_low": null, "adj_close": 16.7002, "adj_open": null, "adj_volume": null, "symbol": "CIM/PD", "exchange": "XNYS", "date": "2020-05-14T00:00:00+0000"}, {"open": 16.9352, "high": 17.3195, "low": 16.7, "close": 16.72, "volume": 7860.0, "adj_high": null, "adj_low": null, "adj_close": 16.72, "adj_open": null, "adj_volume": null, "symbol": "CIM/PD", "exchange": "XNYS", "date": "2020-05-15T00:00:00+0000"}, {"open": 18.39, "high": 18.3999, "low": 17.1944, "close": 17.31, "volume": 26054.0, "adj_high": null, "adj_low": null, "adj_close": 17.31, "adj_open": null, "adj_volume": null, "symbol": "CIM/PD", "exchange": "XNYS", "date": "2020-05-18T00:00:00+0000"}, {"open": 17.585, "high": 17.6, "low": 17.35, "close": 17.37, "volume": 26579.0, "adj_high": null, "adj_low": null, "adj_close": 17.37, "adj_open": null, "adj_volume": null, "symbol": "CIM/PD", "exchange": "XNYS", "date": "2020-05-19T00:00:00+0000"}, {"open": 17.33, "high": 18.4, "low": 17.33, "close": 17.95, "volume": 42386.0, "adj_high": null, "adj_low": null, "adj_close": 17.95, "adj_open": null, "adj_volume": null, "symbol": "CIM/PD", "exchange": "XNYS", "date": "2020-05-20T00:00:00+0000"}, {"open": 17.8006, "high": 18.2499, "low": 17.76, "close": 17.9302, "volume": 28568.0, "adj_high": null, "adj_low": null, "adj_close": 17.9302, "adj_open": null, "adj_volume": null, "symbol": "CIM/PD", "exchange": "XNYS", "date": "2020-05-21T00:00:00+0000"}, {"open": 18.05, "high": 18.08, "low": 17.92, "close": 18.0, "volume": 16131.0, "adj_high": null, "adj_low": null, "adj_close": 18.0, "adj_open": null, "adj_volume": null, "symbol": "CIM/PD", "exchange": "XNYS", "date": "2020-05-22T00:00:00+0000"}, {"open": 18.1, "high": 18.5, "low": 18.02, "close": 18.18, "volume": 154507.0, "adj_high": null, "adj_low": null, "adj_close": 18.18, "adj_open": null, "adj_volume": null, "symbol": "CIM/PD", "exchange": "XNYS", "date": "2020-05-26T00:00:00+0000"}, {"open": 18.35, "high": 18.5924, "low": 18.25, "close": 18.3, "volume": 111102.0, "adj_high": null, "adj_low": null, "adj_close": 18.3, "adj_open": null, "adj_volume": null, "symbol": "CIM/PD", "exchange": "XNYS", "date": "2020-05-27T00:00:00+0000"}, {"open": 18.53, "high": 18.7, "low": 18.3085, "close": 18.5, "volume": 107195.0, "adj_high": null, "adj_low": null, "adj_close": 18.5, "adj_open": null, "adj_volume": null, "symbol": "CIM/PD", "exchange": "XNYS", "date": "2020-05-28T00:00:00+0000"}, {"open": 18.6281, "high": 18.68, "low": 18.35, "close": 18.4, "volume": 19179.0, "adj_high": null, "adj_low": null, "adj_close": 18.4, "adj_open": null, "adj_volume": null, "symbol": "CIM/PD", "exchange": "XNYS", "date": "2020-05-29T00:00:00+0000"}, {"open": 18.65, "high": 19.2, "low": 18.5, "close": 18.99, "volume": 32760.0, "adj_high": null, "adj_low": null, "adj_close": 18.99, "adj_open": null, "adj_volume": null, "symbol": "CIM/PD", "exchange": "XNYS", "date": "2020-06-01T00:00:00+0000"}, {"open": 18.99, "high": 19.14, "low": 18.82, "close": 19.12, "volume": 30132.0, "adj_high": null, "adj_low": null, "adj_close": 19.12, "adj_open": null, "adj_volume": null, "symbol": "CIM/PD", "exchange": "XNYS", "date": "2020-06-02T00:00:00+0000"}, {"open": 19.29, "high": 20.25, "low": 19.09, "close": 20.23, "volume": 44898.0, "adj_high": null, "adj_low": null, "adj_close": 20.23, "adj_open": null, "adj_volume": null, "symbol": "CIM/PD", "exchange": "XNYS", "date": "2020-06-03T00:00:00+0000"}, {"open": 20.0, "high": 21.09, "low": 20.0, "close": 20.94, "volume": 94775.0, "adj_high": null, "adj_low": null, "adj_close": 20.94, "adj_open": null, "adj_volume": null, "symbol": "CIM/PD", "exchange": "XNYS", "date": "2020-06-04T00:00:00+0000"}, {"open": 22.51, "high": 22.51, "low": 21.45, "close": 21.48, "volume": 106739.0, "adj_high": null, "adj_low": null, "adj_close": 21.48, "adj_open": null, "adj_volume": null, "symbol": "CIM/PD", "exchange": "XNYS", "date": "2020-06-05T00:00:00+0000"}, {"open": 21.6, "high": 22.3599, "low": 21.6, "close": 22.16, "volume": 61699.0, "adj_high": null, "adj_low": null, "adj_close": 22.16, "adj_open": null, "adj_volume": null, "symbol": "CIM/PD", "exchange": "XNYS", "date": "2020-06-08T00:00:00+0000"}, {"open": 21.65, "high": 21.85, "low": 21.48, "close": 21.65, "volume": 63179.0, "adj_high": null, "adj_low": null, "adj_close": 21.65, "adj_open": null, "adj_volume": null, "symbol": "CIM/PD", "exchange": "XNYS", "date": "2020-06-09T00:00:00+0000"}, {"open": 21.5, "high": 21.68, "low": 21.25, "close": 21.6, "volume": 62588.0, "adj_high": null, "adj_low": null, "adj_close": 21.6, "adj_open": null, "adj_volume": null, "symbol": "CIM/PD", "exchange": "XNYS", "date": "2020-06-10T00:00:00+0000"}, {"open": 20.95, "high": 20.95, "low": 18.38, "close": 20.3, "volume": 119687.0, "adj_high": null, "adj_low": null, "adj_close": 20.3, "adj_open": null, "adj_volume": null, "symbol": "CIM/PD", "exchange": "XNYS", "date": "2020-06-11T00:00:00+0000"}, {"open": 20.6406, "high": 20.72, "low": 19.65, "close": 20.01, "volume": 32447.0, "adj_high": null, "adj_low": null, "adj_close": 20.01, "adj_open": null, "adj_volume": null, "symbol": "CIM/PD", "exchange": "XNYS", "date": "2020-06-12T00:00:00+0000"}, {"open": 19.6, "high": 19.99, "low": 19.6, "close": 19.89, "volume": 28095.0, "adj_high": null, "adj_low": null, "adj_close": 19.89, "adj_open": null, "adj_volume": null, "symbol": "CIM/PD", "exchange": "XNYS", "date": "2020-06-15T00:00:00+0000"}, {"open": 20.32, "high": 20.77, "low": 19.805, "close": 20.0, "volume": 21756.0, "adj_high": null, "adj_low": null, "adj_close": 20.0, "adj_open": null, "adj_volume": null, "symbol": "CIM/PD", "exchange": "XNYS", "date": "2020-06-16T00:00:00+0000"}, {"open": 20.3, "high": 20.315, "low": 20.01, "close": 20.09, "volume": 20457.0, "adj_high": null, "adj_low": null, "adj_close": 20.09, "adj_open": null, "adj_volume": null, "symbol": "CIM/PD", "exchange": "XNYS", "date": "2020-06-17T00:00:00+0000"}, {"open": 20.0, "high": 20.143, "low": 19.7, "close": 19.94, "volume": 19623.0, "adj_high": null, "adj_low": null, "adj_close": 19.94, "adj_open": null, "adj_volume": null, "symbol": "CIM/PD", "exchange": "XNYS", "date": "2020-06-18T00:00:00+0000"}, {"open": 19.828, "high": 20.08, "low": 19.6, "close": 19.7, "volume": 17665.0, "adj_high": null, "adj_low": null, "adj_close": 19.7, "adj_open": null, "adj_volume": null, "symbol": "CIM/PD", "exchange": "XNYS", "date": "2020-06-19T00:00:00+0000"}, {"open": 19.55, "high": 19.805, "low": 19.41, "close": 19.79, "volume": 19021.0, "adj_high": null, "adj_low": null, "adj_close": 19.79, "adj_open": null, "adj_volume": null, "symbol": "CIM/PD", "exchange": "XNYS", "date": "2020-06-22T00:00:00+0000"}, {"open": 19.86, "high": 20.19, "low": 19.76, "close": 20.19, "volume": 55312.0, "adj_high": null, "adj_low": null, "adj_close": 20.19, "adj_open": null, "adj_volume": null, "symbol": "CIM/PD", "exchange": "XNYS", "date": "2020-06-23T00:00:00+0000"}, {"open": 20.225, "high": 20.225, "low": 19.955, "close": 20.08, "volume": 25445.0, "adj_high": null, "adj_low": null, "adj_close": 20.08, "adj_open": null, "adj_volume": null, "symbol": "CIM/PD", "exchange": "XNYS", "date": "2020-06-24T00:00:00+0000"}, {"open": 20.1, "high": 20.18, "low": 19.85, "close": 19.94, "volume": 26188.0, "adj_high": null, "adj_low": null, "adj_close": 19.94, "adj_open": null, "adj_volume": null, "symbol": "CIM/PD", "exchange": "XNYS", "date": "2020-06-25T00:00:00+0000"}, {"open": 19.94, "high": 20.14, "low": 19.41, "close": 20.14, "volume": 21981.0, "adj_high": null, "adj_low": null, "adj_close": 20.14, "adj_open": null, "adj_volume": null, "symbol": "CIM/PD", "exchange": "XNYS", "date": "2020-06-26T00:00:00+0000"}, {"open": 19.46, "high": 19.815, "low": 19.35, "close": 19.74, "volume": 13095.0, "adj_high": null, "adj_low": null, "adj_close": 19.74, "adj_open": null, "adj_volume": null, "symbol": "CIM/PD", "exchange": "XNYS", "date": "2020-06-29T00:00:00+0000"}, {"open": 19.8, "high": 19.9899, "low": 19.08, "close": 19.14, "volume": 69232.0, "adj_high": null, "adj_low": null, "adj_close": 19.14, "adj_open": null, "adj_volume": null, "symbol": "CIM/PD", "exchange": "XNYS", "date": "2020-06-30T00:00:00+0000"}, {"open": 19.34, "high": 19.5623, "low": 19.3306, "close": 19.37, "volume": 9952.0, "adj_high": null, "adj_low": null, "adj_close": 19.37, "adj_open": null, "adj_volume": null, "symbol": "CIM/PD", "exchange": "XNYS", "date": "2020-07-01T00:00:00+0000"}, {"open": 19.55, "high": 19.68, "low": 19.53, "close": 19.576, "volume": 7098.0, "adj_high": null, "adj_low": null, "adj_close": 19.576, "adj_open": null, "adj_volume": null, "symbol": "CIM/PD", "exchange": "XNYS", "date": "2020-07-02T00:00:00+0000"}, {"open": 19.655, "high": 19.79, "low": 19.435, "close": 19.435, "volume": 3364.0, "adj_high": null, "adj_low": null, "adj_close": 19.435, "adj_open": null, "adj_volume": null, "symbol": "CIM/PD", "exchange": "XNYS", "date": "2020-07-06T00:00:00+0000"}, {"open": 19.4, "high": 19.425, "low": 19.0, "close": 19.055, "volume": 14912.0, "adj_high": null, "adj_low": null, "adj_close": 19.055, "adj_open": null, "adj_volume": null, "symbol": "CIM/PD", "exchange": "XNYS", "date": "2020-07-07T00:00:00+0000"}, {"open": 19.185, "high": 19.25, "low": 19.08, "close": 19.1, "volume": 24620.0, "adj_high": null, "adj_low": null, "adj_close": 19.1, "adj_open": null, "adj_volume": null, "symbol": "CIM/PD", "exchange": "XNYS", "date": "2020-07-08T00:00:00+0000"}, {"open": 19.03, "high": 19.0916, "low": 18.22, "close": 18.525, "volume": 35752.0, "adj_high": null, "adj_low": null, "adj_close": 18.525, "adj_open": null, "adj_volume": null, "symbol": "CIM/PD", "exchange": "XNYS", "date": "2020-07-09T00:00:00+0000"}, {"open": 18.44, "high": 18.44, "low": 18.0, "close": 18.27, "volume": 29753.0, "adj_high": null, "adj_low": null, "adj_close": 18.27, "adj_open": null, "adj_volume": null, "symbol": "CIM/PD", "exchange": "XNYS", "date": "2020-07-10T00:00:00+0000"}, {"open": 18.35, "high": 18.365, "low": 18.0801, "close": 18.16, "volume": 52266.0, "adj_high": null, "adj_low": null, "adj_close": 18.16, "adj_open": null, "adj_volume": null, "symbol": "CIM/PD", "exchange": "XNYS", "date": "2020-07-13T00:00:00+0000"}, {"open": 18.12, "high": 18.26, "low": 18.1, "close": 18.17, "volume": 11401.0, "adj_high": null, "adj_low": null, "adj_close": 18.17, "adj_open": null, "adj_volume": null, "symbol": "CIM/PD", "exchange": "XNYS", "date": "2020-07-14T00:00:00+0000"}, {"open": 18.2198, "high": 18.6, "low": 18.2198, "close": 18.41, "volume": 27126.0, "adj_high": null, "adj_low": null, "adj_close": 18.41, "adj_open": null, "adj_volume": null, "symbol": "CIM/PD", "exchange": "XNYS", "date": "2020-07-15T00:00:00+0000"}]}