{"pagination": {"limit": 10000, "offset": 0, "count": 221, "total": 221}, "data": [{"open": 16.88, "high": 17.13, "low": 16.63, "close": 16.7, "volume": 3826589.0, "adj_high": 17.13, "adj_low": 16.63, "adj_close": 16.7, "adj_open": 16.88, "adj_volume": 3826589.0, "symbol": "NRF", "exchange": "XNYS", "date": "2016-01-04T00:00:00+0000"}, {"open": 16.69, "high": 16.8, "low": 16.33, "close": 16.7, "volume": 2865909.0, "adj_high": 16.8, "adj_low": 16.33, "adj_close": 16.7, "adj_open": 16.69, "adj_volume": 2865909.0, "symbol": "NRF", "exchange": "XNYS", "date": "2016-01-05T00:00:00+0000"}, {"open": 16.53, "high": 16.81, "low": 16.29, "close": 16.66, "volume": 3837353.0, "adj_high": 16.81, "adj_low": 16.29, "adj_close": 16.66, "adj_open": 16.53, "adj_volume": 3837353.0, "symbol": "NRF", "exchange": "XNYS", "date": "2016-01-06T00:00:00+0000"}, {"open": 16.46, "high": 16.47, "low": 15.41, "close": 15.43, "volume": 4645655.0, "adj_high": 16.47, "adj_low": 15.41, "adj_close": 15.43, "adj_open": 16.46, "adj_volume": 4645655.0, "symbol": "NRF", "exchange": "XNYS", "date": "2016-01-07T00:00:00+0000"}, {"open": 15.82, "high": 15.89, "low": 14.88, "close": 14.96, "volume": 5540370.0, "adj_high": 15.89, "adj_low": 14.88, "adj_close": 14.96, "adj_open": 15.82, "adj_volume": 5540370.0, "symbol": "NRF", "exchange": "XNYS", "date": "2016-01-08T00:00:00+0000"}, {"open": 15.07, "high": 15.24, "low": 14.28, "close": 14.5, "volume": 6079685.0, "adj_high": 15.24, "adj_low": 14.28, "adj_close": 14.5, "adj_open": 15.07, "adj_volume": 6079685.0, "symbol": "NRF", "exchange": "XNYS", "date": "2016-01-11T00:00:00+0000"}, {"open": 14.62, "high": 14.66, "low": 13.7, "close": 14.03, "volume": 5278024.0, "adj_high": 14.66, "adj_low": 13.7, "adj_close": 14.03, "adj_open": 14.62, "adj_volume": 5278024.0, "symbol": "NRF", "exchange": "XNYS", "date": "2016-01-12T00:00:00+0000"}, {"open": 14.09, "high": 14.38, "low": 12.91, "close": 13.1, "volume": 7110208.0, "adj_high": 14.38, "adj_low": 12.91, "adj_close": 13.1, "adj_open": 14.09, "adj_volume": 7110208.0, "symbol": "NRF", "exchange": "XNYS", "date": "2016-01-13T00:00:00+0000"}, {"open": 12.32, "high": 12.42, "low": 11.62, "close": 11.65, "volume": 6480795.0, "adj_high": 12.42, "adj_low": 11.62, "adj_close": 11.65, "adj_open": 12.32, "adj_volume": 6480795.0, "symbol": "NRF", "exchange": "XNYS", "date": "2016-01-19T00:00:00+0000"}, {"open": 11.44, "high": 11.47, "low": 10.21, "close": 11.2, "volume": 6840120.0, "adj_high": 11.47, "adj_low": 10.21, "adj_close": 11.2, "adj_open": 11.44, "adj_volume": 6840120.0, "symbol": "NRF", "exchange": "XNYS", "date": "2016-01-20T00:00:00+0000"}, {"open": 11.5, "high": 11.9, "low": 11.115, "close": 11.4, "volume": 4997107.0, "adj_high": 11.9, "adj_low": 11.115, "adj_close": 11.4, "adj_open": 11.5, "adj_volume": 4997107.0, "symbol": "NRF", "exchange": "XNYS", "date": "2016-01-21T00:00:00+0000"}, {"open": 11.75, "high": 12.49, "low": 11.68, "close": 12.26, "volume": 8208285.0, "adj_high": 12.49, "adj_low": 11.68, "adj_close": 12.26, "adj_open": 11.75, "adj_volume": 8208285.0, "symbol": "NRF", "exchange": "XNYS", "date": "2016-01-22T00:00:00+0000"}, {"open": 12.2, "high": 12.39, "low": 11.49, "close": 11.5, "volume": 4158204.0, "adj_high": 12.39, "adj_low": 11.49, "adj_close": 11.5, "adj_open": 12.2, "adj_volume": 4158204.0, "symbol": "NRF", "exchange": "XNYS", "date": "2016-01-25T00:00:00+0000"}, {"open": 11.61, "high": 12.06, "low": 11.425, "close": 11.95, "volume": 3563271.0, "adj_high": 12.06, "adj_low": 11.425, "adj_close": 11.95, "adj_open": 11.61, "adj_volume": 3563271.0, "symbol": "NRF", "exchange": "XNYS", "date": "2016-01-26T00:00:00+0000"}, {"open": 11.89, "high": 12.4798, "low": 11.78, "close": 12.25, "volume": 4908300.0, "adj_high": 12.4798, "adj_low": 11.78, "adj_close": 12.25, "adj_open": 11.89, "adj_volume": 4908300.0, "symbol": "NRF", "exchange": "XNYS", "date": "2016-01-27T00:00:00+0000"}, {"open": 12.45, "high": 12.47, "low": 11.6999, "close": 11.78, "volume": 4413729.0, "adj_high": 12.47, "adj_low": 11.6999, "adj_close": 11.78, "adj_open": 12.45, "adj_volume": 4413729.0, "symbol": "NRF", "exchange": "XNYS", "date": "2016-01-28T00:00:00+0000"}, {"open": 11.86, "high": 12.0, "low": 11.73, "close": 11.87, "volume": 4094517.0, "adj_high": 12.0, "adj_low": 11.73, "adj_close": 11.87, "adj_open": 11.86, "adj_volume": 4094517.0, "symbol": "NRF", "exchange": "XNYS", "date": "2016-01-29T00:00:00+0000"}, {"open": 11.87, "high": 11.9, "low": 11.52, "close": 11.69, "volume": 4102150.0, "adj_high": 11.9, "adj_low": 11.52, "adj_close": 11.69, "adj_open": 11.87, "adj_volume": 4102150.0, "symbol": "NRF", "exchange": "XNYS", "date": "2016-02-01T00:00:00+0000"}, {"open": 11.59, "high": 11.59, "low": 10.98, "close": 11.08, "volume": 4526624.0, "adj_high": 11.59, "adj_low": 10.98, "adj_close": 11.08, "adj_open": 11.59, "adj_volume": 4526624.0, "symbol": "NRF", "exchange": "XNYS", "date": "2016-02-02T00:00:00+0000"}, {"open": 11.22, "high": 11.515, "low": 10.66, "close": 11.41, "volume": 5109635.0, "adj_high": 11.515, "adj_low": 10.66, "adj_close": 11.41, "adj_open": 11.22, "adj_volume": 5109635.0, "symbol": "NRF", "exchange": "XNYS", "date": "2016-02-03T00:00:00+0000"}, {"open": 11.35, "high": 11.71, "low": 11.04, "close": 11.46, "volume": 3377735.0, "adj_high": 11.71, "adj_low": 11.04, "adj_close": 11.46, "adj_open": 11.35, "adj_volume": 3377735.0, "symbol": "NRF", "exchange": "XNYS", "date": "2016-02-04T00:00:00+0000"}, {"open": 11.39, "high": 11.39, "low": 10.975, "close": 11.13, "volume": 3547042.0, "adj_high": 11.39, "adj_low": 10.975, "adj_close": 11.13, "adj_open": 11.39, "adj_volume": 3547042.0, "symbol": "NRF", "exchange": "XNYS", "date": "2016-02-05T00:00:00+0000"}, {"open": 10.97, "high": 10.98, "low": 10.0, "close": 10.36, "volume": 3639122.0, "adj_high": 10.98, "adj_low": 10.0, "adj_close": 10.36, "adj_open": 10.97, "adj_volume": 3639122.0, "symbol": "NRF", "exchange": "XNYS", "date": "2016-02-08T00:00:00+0000"}, {"open": 10.02, "high": 10.02, "low": 8.38, "close": 8.57, "volume": 12312966.0, "adj_high": 10.02, "adj_low": 8.38, "adj_close": 8.57, "adj_open": 10.02, "adj_volume": 12312966.0, "symbol": "NRF", "exchange": "XNYS", "date": "2016-02-09T00:00:00+0000"}, {"open": 8.67, "high": 9.64, "low": 8.52, "close": 9.58, "volume": 5957159.0, "adj_high": 9.64, "adj_low": 8.52, "adj_close": 9.58, "adj_open": 8.67, "adj_volume": 5957159.0, "symbol": "NRF", "exchange": "XNYS", "date": "2016-02-10T00:00:00+0000"}, {"open": 9.38, "high": 9.5, "low": 8.72, "close": 8.97, "volume": 6097398.0, "adj_high": 9.5, "adj_low": 8.72, "adj_close": 8.97, "adj_open": 9.38, "adj_volume": 6097398.0, "symbol": "NRF", "exchange": "XNYS", "date": "2016-02-11T00:00:00+0000"}, {"open": 9.03, "high": 9.425, "low": 8.92, "close": 9.37, "volume": 5588123.0, "adj_high": 9.425, "adj_low": 8.92, "adj_close": 9.37, "adj_open": 9.03, "adj_volume": 5588123.0, "symbol": "NRF", "exchange": "XNYS", "date": "2016-02-12T00:00:00+0000"}, {"open": 9.39, "high": 9.65, "low": 9.06, "close": 9.39, "volume": 5168629.0, "adj_high": 9.65, "adj_low": 9.06, "adj_close": 9.39, "adj_open": 9.39, "adj_volume": 5168629.0, "symbol": "NRF", "exchange": "XNYS", "date": "2016-02-16T00:00:00+0000"}, {"open": 9.51, "high": 10.35, "low": 9.45, "close": 10.35, "volume": 6031366.0, "adj_high": 10.35, "adj_low": 9.45, "adj_close": 10.35, "adj_open": 9.51, "adj_volume": 6031366.0, "symbol": "NRF", "exchange": "XNYS", "date": "2016-02-17T00:00:00+0000"}, {"open": 10.4, "high": 10.48, "low": 9.7919, "close": 10.2, "volume": 4112589.0, "adj_high": 10.48, "adj_low": 9.7919, "adj_close": 10.2, "adj_open": 10.4, "adj_volume": 4112589.0, "symbol": "NRF", "exchange": "XNYS", "date": "2016-02-18T00:00:00+0000"}, {"open": 10.13, "high": 10.13, "low": 9.6, "close": 9.99, "volume": 3322519.0, "adj_high": 10.13, "adj_low": 9.6, "adj_close": 9.99, "adj_open": 10.13, "adj_volume": 3322519.0, "symbol": "NRF", "exchange": "XNYS", "date": "2016-02-19T00:00:00+0000"}, {"open": 10.11, "high": 10.37, "low": 10.1, "close": 10.28, "volume": 4569048.0, "adj_high": 10.37, "adj_low": 10.1, "adj_close": 10.28, "adj_open": 10.11, "adj_volume": 4569048.0, "symbol": "NRF", "exchange": "XNYS", "date": "2016-02-22T00:00:00+0000"}, {"open": 10.2, "high": 10.39, "low": 10.13, "close": 10.31, "volume": 2234596.0, "adj_high": 10.39, "adj_low": 10.13, "adj_close": 10.31, "adj_open": 10.2, "adj_volume": 2234596.0, "symbol": "NRF", "exchange": "XNYS", "date": "2016-02-23T00:00:00+0000"}, {"open": 10.14, "high": 10.77, "low": 9.925, "close": 10.73, "volume": 4556384.0, "adj_high": 10.77, "adj_low": 9.925, "adj_close": 10.73, "adj_open": 10.14, "adj_volume": 4556384.0, "symbol": "NRF", "exchange": "XNYS", "date": "2016-02-24T00:00:00+0000"}, {"open": 13.14, "high": 13.36, "low": 11.91, "close": 12.47, "volume": 24038382.0, "adj_high": 13.36, "adj_low": 11.91, "adj_close": 12.47, "adj_open": 13.14, "adj_volume": 24038382.0, "symbol": "NRF", "exchange": "XNYS", "date": "2016-02-25T00:00:00+0000"}, {"open": 13.3, "high": 13.42, "low": 12.16, "close": 12.35, "volume": 10166976.0, "adj_high": 13.42, "adj_low": 12.16, "adj_close": 12.35, "adj_open": 13.3, "adj_volume": 10166976.0, "symbol": "NRF", "exchange": "XNYS", "date": "2016-02-26T00:00:00+0000"}, {"open": 12.44, "high": 12.9, "low": 12.25, "close": 12.78, "volume": 5483234.0, "adj_high": 12.9, "adj_low": 12.25, "adj_close": 12.78, "adj_open": 12.44, "adj_volume": 5483234.0, "symbol": "NRF", "exchange": "XNYS", "date": "2016-03-01T00:00:00+0000"}, {"open": 12.76, "high": 13.3, "low": 12.63, "close": 13.08, "volume": 4571678.0, "adj_high": 13.3, "adj_low": 12.63, "adj_close": 13.08, "adj_open": 12.76, "adj_volume": 4571678.0, "symbol": "NRF", "exchange": "XNYS", "date": "2016-03-02T00:00:00+0000"}, {"open": 12.74, "high": 13.35, "low": 12.6, "close": 13.14, "volume": 4158539.0, "adj_high": 13.35, "adj_low": 12.6, "adj_close": 13.14, "adj_open": 12.74, "adj_volume": 4158539.0, "symbol": "NRF", "exchange": "XNYS", "date": "2016-03-03T00:00:00+0000"}, {"open": 13.19, "high": 13.57, "low": 12.825, "close": 12.94, "volume": 5320027.0, "adj_high": 13.57, "adj_low": 12.825, "adj_close": 12.94, "adj_open": 13.19, "adj_volume": 5320027.0, "symbol": "NRF", "exchange": "XNYS", "date": "2016-03-04T00:00:00+0000"}, {"open": 12.81, "high": 13.28, "low": 12.78, "close": 13.19, "volume": 3245285.0, "adj_high": 13.28, "adj_low": 12.78, "adj_close": 13.19, "adj_open": 12.81, "adj_volume": 3245285.0, "symbol": "NRF", "exchange": "XNYS", "date": "2016-03-07T00:00:00+0000"}, {"open": 13.12, "high": 13.3, "low": 12.5, "close": 12.7, "volume": 3531398.0, "adj_high": 13.3, "adj_low": 12.5, "adj_close": 12.7, "adj_open": 13.12, "adj_volume": 3531398.0, "symbol": "NRF", "exchange": "XNYS", "date": "2016-03-08T00:00:00+0000"}, {"open": 12.77, "high": 13.04, "low": 12.664, "close": 12.92, "volume": 2574598.0, "adj_high": 13.04, "adj_low": 12.664, "adj_close": 12.92, "adj_open": 12.77, "adj_volume": 2574598.0, "symbol": "NRF", "exchange": "XNYS", "date": "2016-03-09T00:00:00+0000"}, {"open": 13.05, "high": 13.1, "low": 12.45, "close": 12.69, "volume": 3373168.0, "adj_high": 13.1, "adj_low": 12.45, "adj_close": 12.69, "adj_open": 13.05, "adj_volume": 3373168.0, "symbol": "NRF", "exchange": "XNYS", "date": "2016-03-10T00:00:00+0000"}, {"open": 12.85, "high": 13.5736, "low": 12.85, "close": 13.27, "volume": 3910565.0, "adj_high": 13.5736, "adj_low": 12.85, "adj_close": 13.27, "adj_open": 12.85, "adj_volume": 3910565.0, "symbol": "NRF", "exchange": "XNYS", "date": "2016-03-11T00:00:00+0000"}, {"open": 13.14, "high": 13.18, "low": 12.7, "close": 13.03, "volume": 2766296.0, "adj_high": 13.18, "adj_low": 12.7, "adj_close": 13.03, "adj_open": 13.14, "adj_volume": 2766296.0, "symbol": "NRF", "exchange": "XNYS", "date": "2016-03-14T00:00:00+0000"}, {"open": 12.92, "high": 12.991, "low": 12.5, "close": 12.8, "volume": 2616080.0, "adj_high": 12.991, "adj_low": 12.5, "adj_close": 12.8, "adj_open": 12.92, "adj_volume": 2616080.0, "symbol": "NRF", "exchange": "XNYS", "date": "2016-03-15T00:00:00+0000"}, {"open": 12.72, "high": 12.94, "low": 12.43, "close": 12.77, "volume": 3974915.0, "adj_high": 12.94, "adj_low": 12.43, "adj_close": 12.77, "adj_open": 12.72, "adj_volume": 3974915.0, "symbol": "NRF", "exchange": "XNYS", "date": "2016-03-16T00:00:00+0000"}, {"open": 12.86, "high": 13.04, "low": 12.71, "close": 12.97, "volume": 2109293.0, "adj_high": 13.04, "adj_low": 12.71, "adj_close": 12.97, "adj_open": 12.86, "adj_volume": 2109293.0, "symbol": "NRF", "exchange": "XNYS", "date": "2016-03-17T00:00:00+0000"}, {"open": 12.98, "high": 13.13, "low": 12.51, "close": 12.55, "volume": 4618743.0, "adj_high": 13.13, "adj_low": 12.51, "adj_close": 12.55, "adj_open": 12.98, "adj_volume": 4618743.0, "symbol": "NRF", "exchange": "XNYS", "date": "2016-03-18T00:00:00+0000"}, {"open": 12.54, "high": 12.925, "low": 12.53, "close": 12.76, "volume": 2777081.0, "adj_high": 12.925, "adj_low": 12.53, "adj_close": 12.76, "adj_open": 12.54, "adj_volume": 2777081.0, "symbol": "NRF", "exchange": "XNYS", "date": "2016-03-21T00:00:00+0000"}, {"open": 12.66, "high": 13.0, "low": 12.54, "close": 12.78, "volume": 3236767.0, "adj_high": 13.0, "adj_low": 12.54, "adj_close": 12.78, "adj_open": 12.66, "adj_volume": 3236767.0, "symbol": "NRF", "exchange": "XNYS", "date": "2016-03-22T00:00:00+0000"}, {"open": 12.73, "high": 12.8, "low": 12.36, "close": 12.36, "volume": 2887834.0, "adj_high": 12.8, "adj_low": 12.36, "adj_close": 12.36, "adj_open": 12.73, "adj_volume": 2887834.0, "symbol": "NRF", "exchange": "XNYS", "date": "2016-03-23T00:00:00+0000"}, {"open": 12.29, "high": 12.63, "low": 12.05, "close": 12.56, "volume": 2633538.0, "adj_high": 12.63, "adj_low": 12.05, "adj_close": 12.56, "adj_open": 12.29, "adj_volume": 2633538.0, "symbol": "NRF", "exchange": "XNYS", "date": "2016-03-24T00:00:00+0000"}, {"open": 12.6, "high": 12.7, "low": 12.2799, "close": 12.51, "volume": 1677274.0, "adj_high": 12.7, "adj_low": 12.2799, "adj_close": 12.51, "adj_open": 12.6, "adj_volume": 1677274.0, "symbol": "NRF", "exchange": "XNYS", "date": "2016-03-28T00:00:00+0000"}, {"open": 12.98, "high": 13.06, "low": 12.79, "close": 12.96, "volume": 2351182.0, "adj_high": 13.06, "adj_low": 12.79, "adj_close": 12.96, "adj_open": 12.98, "adj_volume": 2351182.0, "symbol": "NRF", "exchange": "XNYS", "date": "2016-04-01T00:00:00+0000"}, {"open": 12.91, "high": 13.09, "low": 12.79, "close": 12.81, "volume": 1259447.0, "adj_high": 13.09, "adj_low": 12.79, "adj_close": 12.81, "adj_open": 12.91, "adj_volume": 1259447.0, "symbol": "NRF", "exchange": "XNYS", "date": "2016-04-04T00:00:00+0000"}, {"open": 12.7, "high": 12.89, "low": 12.6, "close": 12.73, "volume": 1205252.0, "adj_high": 12.89, "adj_low": 12.6, "adj_close": 12.73, "adj_open": 12.7, "adj_volume": 1205252.0, "symbol": "NRF", "exchange": "XNYS", "date": "2016-04-05T00:00:00+0000"}, {"open": 12.75, "high": 12.885, "low": 12.7, "close": 12.87, "volume": 1313957.0, "adj_high": 12.885, "adj_low": 12.7, "adj_close": 12.87, "adj_open": 12.75, "adj_volume": 1313957.0, "symbol": "NRF", "exchange": "XNYS", "date": "2016-04-06T00:00:00+0000"}, {"open": 12.76, "high": 12.98, "low": 12.39, "close": 12.48, "volume": 1947550.0, "adj_high": 12.98, "adj_low": 12.39, "adj_close": 12.48, "adj_open": 12.76, "adj_volume": 1947550.0, "symbol": "NRF", "exchange": "XNYS", "date": "2016-04-07T00:00:00+0000"}, {"open": 12.54, "high": 12.94, "low": 12.54, "close": 12.66, "volume": 1739828.0, "adj_high": 12.94, "adj_low": 12.54, "adj_close": 12.66, "adj_open": 12.54, "adj_volume": 1739828.0, "symbol": "NRF", "exchange": "XNYS", "date": "2016-04-08T00:00:00+0000"}, {"open": 12.75, "high": 12.965, "low": 12.6101, "close": 12.73, "volume": 1291864.0, "adj_high": 12.965, "adj_low": 12.6101, "adj_close": 12.73, "adj_open": 12.75, "adj_volume": 1291864.0, "symbol": "NRF", "exchange": "XNYS", "date": "2016-04-11T00:00:00+0000"}, {"open": 12.81, "high": 13.0, "low": 12.73, "close": 12.97, "volume": 1635937.0, "adj_high": 13.0, "adj_low": 12.73, "adj_close": 12.97, "adj_open": 12.81, "adj_volume": 1635937.0, "symbol": "NRF", "exchange": "XNYS", "date": "2016-04-12T00:00:00+0000"}, {"open": 13.04, "high": 13.4, "low": 12.97, "close": 13.14, "volume": 2270468.0, "adj_high": 13.4, "adj_low": 12.97, "adj_close": 13.14, "adj_open": 13.04, "adj_volume": 2270468.0, "symbol": "NRF", "exchange": "XNYS", "date": "2016-04-13T00:00:00+0000"}, {"open": 13.15, "high": 13.23, "low": 13.025, "close": 13.07, "volume": 1618124.0, "adj_high": 13.23, "adj_low": 13.025, "adj_close": 13.07, "adj_open": 13.15, "adj_volume": 1618124.0, "symbol": "NRF", "exchange": "XNYS", "date": "2016-04-14T00:00:00+0000"}, {"open": 13.07, "high": 13.26, "low": 13.05, "close": 13.16, "volume": 2688500.0, "adj_high": 13.26, "adj_low": 13.05, "adj_close": 13.16, "adj_open": 13.07, "adj_volume": 2688500.0, "symbol": "NRF", "exchange": "XNYS", "date": "2016-04-15T00:00:00+0000"}, {"open": 13.12, "high": 13.1799, "low": 12.9, "close": 12.98, "volume": 2661004.0, "adj_high": 13.1799, "adj_low": 12.9, "adj_close": 12.98, "adj_open": 13.12, "adj_volume": 2661004.0, "symbol": "NRF", "exchange": "XNYS", "date": "2016-04-18T00:00:00+0000"}, {"open": 13.0, "high": 13.3561, "low": 12.95, "close": 13.15, "volume": 3263120.0, "adj_high": 13.3561, "adj_low": 12.95, "adj_close": 13.15, "adj_open": 13.0, "adj_volume": 3263120.0, "symbol": "NRF", "exchange": "XNYS", "date": "2016-04-19T00:00:00+0000"}, {"open": 13.15, "high": 13.42, "low": 13.13, "close": 13.38, "volume": 1785337.0, "adj_high": 13.42, "adj_low": 13.13, "adj_close": 13.38, "adj_open": 13.15, "adj_volume": 1785337.0, "symbol": "NRF", "exchange": "XNYS", "date": "2016-04-20T00:00:00+0000"}, {"open": 12.81, "high": 12.85, "low": 12.425, "close": 12.69, "volume": 2991287.0, "adj_high": 12.85, "adj_low": 12.425, "adj_close": 12.69, "adj_open": 12.81, "adj_volume": 2991287.0, "symbol": "NRF", "exchange": "XNYS", "date": "2016-05-02T00:00:00+0000"}, {"open": 12.6, "high": 12.685, "low": 12.25, "close": 12.44, "volume": 2884266.0, "adj_high": 12.685, "adj_low": 12.25, "adj_close": 12.44, "adj_open": 12.6, "adj_volume": 2884266.0, "symbol": "NRF", "exchange": "XNYS", "date": "2016-05-03T00:00:00+0000"}, {"open": 12.33, "high": 12.63, "low": 12.2, "close": 12.61, "volume": 2733948.0, "adj_high": 12.63, "adj_low": 12.2, "adj_close": 12.61, "adj_open": 12.33, "adj_volume": 2733948.0, "symbol": "NRF", "exchange": "XNYS", "date": "2016-05-04T00:00:00+0000"}, {"open": 12.71, "high": 12.83, "low": 12.52, "close": 12.71, "volume": 2045837.0, "adj_high": 12.83, "adj_low": 12.52, "adj_close": 12.71, "adj_open": 12.71, "adj_volume": 2045837.0, "symbol": "NRF", "exchange": "XNYS", "date": "2016-05-05T00:00:00+0000"}, {"open": 12.7, "high": 13.01, "low": 12.62, "close": 13.0, "volume": 2992715.0, "adj_high": 13.01, "adj_low": 12.62, "adj_close": 13.0, "adj_open": 12.7, "adj_volume": 2992715.0, "symbol": "NRF", "exchange": "XNYS", "date": "2016-05-06T00:00:00+0000"}, {"open": 13.41, "high": 14.395, "low": 13.26, "close": 14.26, "volume": 6186652.0, "adj_high": 14.395, "adj_low": 13.26, "adj_close": 14.26, "adj_open": 13.41, "adj_volume": 6186652.0, "symbol": "NRF", "exchange": "XNYS", "date": "2016-05-09T00:00:00+0000"}, {"open": 14.52, "high": 15.0, "low": 13.689, "close": 13.84, "volume": 4872921.0, "adj_high": 15.0, "adj_low": 13.689, "adj_close": 13.84, "adj_open": 14.52, "adj_volume": 4872921.0, "symbol": "NRF", "exchange": "XNYS", "date": "2016-05-10T00:00:00+0000"}, {"open": 13.39, "high": 13.85, "low": 13.05, "close": 13.1, "volume": 2829400.0, "adj_high": 13.85, "adj_low": 13.05, "adj_close": 13.1, "adj_open": 13.39, "adj_volume": 2829400.0, "symbol": "NRF", "exchange": "XNYS", "date": "2016-05-12T00:00:00+0000"}, {"open": 13.07, "high": 13.36, "low": 12.78, "close": 12.99, "volume": 1881453.0, "adj_high": 13.36, "adj_low": 12.78, "adj_close": 12.99, "adj_open": 13.07, "adj_volume": 1881453.0, "symbol": "NRF", "exchange": "XNYS", "date": "2016-05-13T00:00:00+0000"}, {"open": 13.02, "high": 13.325, "low": 13.02, "close": 13.2, "volume": 1399745.0, "adj_high": 13.325, "adj_low": 13.02, "adj_close": 13.2, "adj_open": 13.02, "adj_volume": 1399745.0, "symbol": "NRF", "exchange": "XNYS", "date": "2016-05-16T00:00:00+0000"}, {"open": 13.13, "high": 13.49, "low": 13.06, "close": 13.29, "volume": 2024605.0, "adj_high": 13.49, "adj_low": 13.06, "adj_close": 13.29, "adj_open": 13.13, "adj_volume": 2024605.0, "symbol": "NRF", "exchange": "XNYS", "date": "2016-05-17T00:00:00+0000"}, {"open": 13.22, "high": 13.4499, "low": 12.96, "close": 13.14, "volume": 2251871.0, "adj_high": 13.4499, "adj_low": 12.96, "adj_close": 13.14, "adj_open": 13.22, "adj_volume": 2251871.0, "symbol": "NRF", "exchange": "XNYS", "date": "2016-05-18T00:00:00+0000"}, {"open": 13.02, "high": 13.145, "low": 12.4, "close": 12.47, "volume": 3190712.0, "adj_high": 13.145, "adj_low": 12.4, "adj_close": 12.47, "adj_open": 13.02, "adj_volume": 3190712.0, "symbol": "NRF", "exchange": "XNYS", "date": "2016-05-19T00:00:00+0000"}, {"open": 12.48, "high": 12.87, "low": 12.35, "close": 12.62, "volume": 2258165.0, "adj_high": 12.87, "adj_low": 12.35, "adj_close": 12.62, "adj_open": 12.48, "adj_volume": 2258165.0, "symbol": "NRF", "exchange": "XNYS", "date": "2016-05-20T00:00:00+0000"}, {"open": 12.6, "high": 12.71, "low": 12.5, "close": 12.58, "volume": 1440541.0, "adj_high": 12.71, "adj_low": 12.5, "adj_close": 12.58, "adj_open": 12.6, "adj_volume": 1440541.0, "symbol": "NRF", "exchange": "XNYS", "date": "2016-05-23T00:00:00+0000"}, {"open": 12.65, "high": 12.685, "low": 12.34, "close": 12.59, "volume": 1553044.0, "adj_high": 12.685, "adj_low": 12.34, "adj_close": 12.59, "adj_open": 12.65, "adj_volume": 1553044.0, "symbol": "NRF", "exchange": "XNYS", "date": "2016-05-24T00:00:00+0000"}, {"open": 12.61, "high": 13.15, "low": 12.5716, "close": 13.15, "volume": 1364547.0, "adj_high": 13.15, "adj_low": 12.5716, "adj_close": 13.15, "adj_open": 12.61, "adj_volume": 1364547.0, "symbol": "NRF", "exchange": "XNYS", "date": "2016-05-25T00:00:00+0000"}, {"open": 13.15, "high": 13.21, "low": 12.98, "close": 13.12, "volume": 1455890.0, "adj_high": 13.21, "adj_low": 12.98, "adj_close": 13.12, "adj_open": 13.15, "adj_volume": 1455890.0, "symbol": "NRF", "exchange": "XNYS", "date": "2016-05-26T00:00:00+0000"}, {"open": 13.09, "high": 13.47, "low": 13.09, "close": 13.35, "volume": 1327407.0, "adj_high": 13.47, "adj_low": 13.09, "adj_close": 13.35, "adj_open": 13.09, "adj_volume": 1327407.0, "symbol": "NRF", "exchange": "XNYS", "date": "2016-05-27T00:00:00+0000"}, {"open": 13.26, "high": 13.53, "low": 13.11, "close": 13.5, "volume": 2708409.0, "adj_high": 13.53, "adj_low": 13.11, "adj_close": 13.5, "adj_open": 13.26, "adj_volume": 2708409.0, "symbol": "NRF", "exchange": "XNYS", "date": "2016-05-31T00:00:00+0000"}, {"open": 13.23, "high": 13.52, "low": 12.85, "close": 13.5, "volume": 2553811.0, "adj_high": 13.52, "adj_low": 12.85, "adj_close": 13.5, "adj_open": 13.23, "adj_volume": 2553811.0, "symbol": "NRF", "exchange": "XNYS", "date": "2016-06-01T00:00:00+0000"}, {"open": 13.43, "high": 13.58, "low": 13.22, "close": 13.48, "volume": 1493141.0, "adj_high": 13.58, "adj_low": 13.22, "adj_close": 13.48, "adj_open": 13.43, "adj_volume": 1493141.0, "symbol": "NRF", "exchange": "XNYS", "date": "2016-06-02T00:00:00+0000"}, {"open": 13.75, "high": 13.98, "low": 12.56, "close": 12.98, "volume": 11865597.0, "adj_high": 13.98, "adj_low": 12.56, "adj_close": 12.98, "adj_open": 13.75, "adj_volume": 11865597.0, "symbol": "NRF", "exchange": "XNYS", "date": "2016-06-03T00:00:00+0000"}, {"open": 13.0, "high": 13.5, "low": 12.93, "close": 12.95, "volume": 5910387.0, "adj_high": 13.5, "adj_low": 12.93, "adj_close": 12.95, "adj_open": 13.0, "adj_volume": 5910387.0, "symbol": "NRF", "exchange": "XNYS", "date": "2016-06-06T00:00:00+0000"}, {"open": 12.97, "high": 13.63, "low": 12.97, "close": 13.27, "volume": 8352151.0, "adj_high": 13.63, "adj_low": 12.97, "adj_close": 13.27, "adj_open": 12.97, "adj_volume": 8352151.0, "symbol": "NRF", "exchange": "XNYS", "date": "2016-06-07T00:00:00+0000"}, {"open": 13.26, "high": 13.82, "low": 13.21, "close": 13.82, "volume": 4200588.0, "adj_high": 13.82, "adj_low": 13.21, "adj_close": 13.82, "adj_open": 13.26, "adj_volume": 4200588.0, "symbol": "NRF", "exchange": "XNYS", "date": "2016-06-08T00:00:00+0000"}, {"open": 13.69, "high": 13.9, "low": 13.6, "close": 13.9, "volume": 2494196.0, "adj_high": 13.9, "adj_low": 13.6, "adj_close": 13.9, "adj_open": 13.69, "adj_volume": 2494196.0, "symbol": "NRF", "exchange": "XNYS", "date": "2016-06-09T00:00:00+0000"}, {"open": 13.68, "high": 13.79, "low": 13.525, "close": 13.56, "volume": 2692672.0, "adj_high": 13.79, "adj_low": 13.525, "adj_close": 13.56, "adj_open": 13.68, "adj_volume": 2692672.0, "symbol": "NRF", "exchange": "XNYS", "date": "2016-06-10T00:00:00+0000"}, {"open": 13.53, "high": 13.76, "low": 13.15, "close": 13.16, "volume": 2579421.0, "adj_high": 13.76, "adj_low": 13.15, "adj_close": 13.16, "adj_open": 13.53, "adj_volume": 2579421.0, "symbol": "NRF", "exchange": "XNYS", "date": "2016-06-13T00:00:00+0000"}, {"open": 13.1, "high": 13.31, "low": 12.1125, "close": 12.51, "volume": 5020958.0, "adj_high": 13.31, "adj_low": 12.1125, "adj_close": 12.51, "adj_open": 13.1, "adj_volume": 5020958.0, "symbol": "NRF", "exchange": "XNYS", "date": "2016-06-14T00:00:00+0000"}, {"open": 12.52, "high": 12.71, "low": 12.44, "close": 12.49, "volume": 3479401.0, "adj_high": 12.71, "adj_low": 12.44, "adj_close": 12.49, "adj_open": 12.52, "adj_volume": 3479401.0, "symbol": "NRF", "exchange": "XNYS", "date": "2016-06-15T00:00:00+0000"}, {"open": 12.42, "high": 12.44, "low": 12.12, "close": 12.3, "volume": 3105912.0, "adj_high": 12.44, "adj_low": 12.12, "adj_close": 12.3, "adj_open": 12.42, "adj_volume": 3105912.0, "symbol": "NRF", "exchange": "XNYS", "date": "2016-06-16T00:00:00+0000"}, {"open": 12.37, "high": 12.6, "low": 12.14, "close": 12.17, "volume": 3964738.0, "adj_high": 12.6, "adj_low": 12.14, "adj_close": 12.17, "adj_open": 12.37, "adj_volume": 3964738.0, "symbol": "NRF", "exchange": "XNYS", "date": "2016-06-17T00:00:00+0000"}, {"open": 12.34, "high": 12.42, "low": 12.15, "close": 12.3, "volume": 3573389.0, "adj_high": 12.42, "adj_low": 12.15, "adj_close": 12.3, "adj_open": 12.34, "adj_volume": 3573389.0, "symbol": "NRF", "exchange": "XNYS", "date": "2016-06-20T00:00:00+0000"}, {"open": 12.29, "high": 12.34, "low": 12.0, "close": 12.06, "volume": 2815693.0, "adj_high": 12.34, "adj_low": 12.0, "adj_close": 12.06, "adj_open": 12.29, "adj_volume": 2815693.0, "symbol": "NRF", "exchange": "XNYS", "date": "2016-06-21T00:00:00+0000"}, {"open": 12.07, "high": 12.07, "low": 11.75, "close": 11.9, "volume": 2648867.0, "adj_high": 12.07, "adj_low": 11.75, "adj_close": 11.9, "adj_open": 12.07, "adj_volume": 2648867.0, "symbol": "NRF", "exchange": "XNYS", "date": "2016-06-22T00:00:00+0000"}, {"open": 12.07, "high": 12.15, "low": 11.864, "close": 12.07, "volume": 2553703.0, "adj_high": 12.15, "adj_low": 11.864, "adj_close": 12.07, "adj_open": 12.07, "adj_volume": 2553703.0, "symbol": "NRF", "exchange": "XNYS", "date": "2016-06-23T00:00:00+0000"}, {"open": 11.75, "high": 11.97, "low": 11.58, "close": 11.66, "volume": 2338256.0, "adj_high": 11.97, "adj_low": 11.58, "adj_close": 11.66, "adj_open": 11.75, "adj_volume": 2338256.0, "symbol": "NRF", "exchange": "XNYS", "date": "2016-06-24T00:00:00+0000"}, {"open": 11.49, "high": 11.52, "low": 10.78, "close": 10.92, "volume": 3225840.0, "adj_high": 11.52, "adj_low": 10.78, "adj_close": 10.92, "adj_open": 11.49, "adj_volume": 3225840.0, "symbol": "NRF", "exchange": "XNYS", "date": "2016-06-27T00:00:00+0000"}, {"open": 11.1, "high": 11.38, "low": 11.001, "close": 11.1, "volume": 2205849.0, "adj_high": 11.38, "adj_low": 11.001, "adj_close": 11.1, "adj_open": 11.1, "adj_volume": 2205849.0, "symbol": "NRF", "exchange": "XNYS", "date": "2016-06-28T00:00:00+0000"}, {"open": 11.17, "high": 11.37, "low": 11.08, "close": 11.29, "volume": 2381513.0, "adj_high": 11.37, "adj_low": 11.08, "adj_close": 11.29, "adj_open": 11.17, "adj_volume": 2381513.0, "symbol": "NRF", "exchange": "XNYS", "date": "2016-06-29T00:00:00+0000"}, {"open": 11.27, "high": 11.43, "low": 11.05, "close": 11.43, "volume": 3068442.0, "adj_high": 11.43, "adj_low": 11.05, "adj_close": 11.43, "adj_open": 11.27, "adj_volume": 3068442.0, "symbol": "NRF", "exchange": "XNYS", "date": "2016-06-30T00:00:00+0000"}, {"open": 11.37, "high": 11.6473, "low": 11.305, "close": 11.46, "volume": 2286992.0, "adj_high": 11.6473, "adj_low": 11.305, "adj_close": 11.46, "adj_open": 11.37, "adj_volume": 2286992.0, "symbol": "NRF", "exchange": "XNYS", "date": "2016-07-01T00:00:00+0000"}, {"open": 11.46, "high": 11.46, "low": 10.82, "close": 10.86, "volume": 2564098.0, "adj_high": 11.46, "adj_low": 10.82, "adj_close": 10.86, "adj_open": 11.46, "adj_volume": 2564098.0, "symbol": "NRF", "exchange": "XNYS", "date": "2016-07-05T00:00:00+0000"}, {"open": 10.8, "high": 11.185, "low": 10.59, "close": 11.04, "volume": 3580563.0, "adj_high": 11.185, "adj_low": 10.59, "adj_close": 11.04, "adj_open": 10.8, "adj_volume": 3580563.0, "symbol": "NRF", "exchange": "XNYS", "date": "2016-07-06T00:00:00+0000"}, {"open": 11.06, "high": 11.13, "low": 10.78, "close": 10.95, "volume": 3181657.0, "adj_high": 11.13, "adj_low": 10.78, "adj_close": 10.95, "adj_open": 11.06, "adj_volume": 3181657.0, "symbol": "NRF", "exchange": "XNYS", "date": "2016-07-07T00:00:00+0000"}, {"open": 11.14, "high": 11.64, "low": 11.04, "close": 11.48, "volume": 3629646.0, "adj_high": 11.64, "adj_low": 11.04, "adj_close": 11.48, "adj_open": 11.14, "adj_volume": 3629646.0, "symbol": "NRF", "exchange": "XNYS", "date": "2016-07-08T00:00:00+0000"}, {"open": 11.58, "high": 12.08, "low": 11.55, "close": 12.05, "volume": 3455137.0, "adj_high": 12.08, "adj_low": 11.55, "adj_close": 12.05, "adj_open": 11.58, "adj_volume": 3455137.0, "symbol": "NRF", "exchange": "XNYS", "date": "2016-07-11T00:00:00+0000"}, {"open": 12.17, "high": 12.515, "low": 12.12, "close": 12.31, "volume": 3406784.0, "adj_high": 12.515, "adj_low": 12.12, "adj_close": 12.31, "adj_open": 12.17, "adj_volume": 3406784.0, "symbol": "NRF", "exchange": "XNYS", "date": "2016-07-12T00:00:00+0000"}, {"open": 12.33, "high": 12.42, "low": 12.16, "close": 12.28, "volume": 1410677.0, "adj_high": 12.42, "adj_low": 12.16, "adj_close": 12.28, "adj_open": 12.33, "adj_volume": 1410677.0, "symbol": "NRF", "exchange": "XNYS", "date": "2016-07-13T00:00:00+0000"}, {"open": 12.38, "high": 12.605, "low": 12.24, "close": 12.56, "volume": 2414647.0, "adj_high": 12.605, "adj_low": 12.24, "adj_close": 12.56, "adj_open": 12.38, "adj_volume": 2414647.0, "symbol": "NRF", "exchange": "XNYS", "date": "2016-07-14T00:00:00+0000"}, {"open": 12.65, "high": 12.66, "low": 12.46, "close": 12.58, "volume": 1315421.0, "adj_high": 12.66, "adj_low": 12.46, "adj_close": 12.58, "adj_open": 12.65, "adj_volume": 1315421.0, "symbol": "NRF", "exchange": "XNYS", "date": "2016-07-15T00:00:00+0000"}, {"open": 12.55, "high": 13.04, "low": 12.54, "close": 12.99, "volume": 2059554.0, "adj_high": 13.04, "adj_low": 12.54, "adj_close": 12.99, "adj_open": 12.55, "adj_volume": 2059554.0, "symbol": "NRF", "exchange": "XNYS", "date": "2016-07-18T00:00:00+0000"}, {"open": 12.91, "high": 13.0, "low": 12.85, "close": 12.98, "volume": 929581.0, "adj_high": 13.0, "adj_low": 12.85, "adj_close": 12.98, "adj_open": 12.91, "adj_volume": 929581.0, "symbol": "NRF", "exchange": "XNYS", "date": "2016-07-19T00:00:00+0000"}, {"open": 12.97, "high": 13.09, "low": 12.92, "close": 12.99, "volume": 2307940.0, "adj_high": 13.09, "adj_low": 12.92, "adj_close": 12.99, "adj_open": 12.97, "adj_volume": 2307940.0, "symbol": "NRF", "exchange": "XNYS", "date": "2016-07-20T00:00:00+0000"}, {"open": 12.99, "high": 13.05, "low": 12.925, "close": 12.96, "volume": 1334195.0, "adj_high": 13.05, "adj_low": 12.925, "adj_close": 12.96, "adj_open": 12.99, "adj_volume": 1334195.0, "symbol": "NRF", "exchange": "XNYS", "date": "2016-07-21T00:00:00+0000"}, {"open": 12.91, "high": 13.0, "low": 12.79, "close": 12.81, "volume": 1418015.0, "adj_high": 13.0, "adj_low": 12.79, "adj_close": 12.81, "adj_open": 12.91, "adj_volume": 1418015.0, "symbol": "NRF", "exchange": "XNYS", "date": "2016-07-22T00:00:00+0000"}, {"open": 12.85, "high": 12.9, "low": 12.76, "close": 12.86, "volume": 1205793.0, "adj_high": 12.9, "adj_low": 12.76, "adj_close": 12.86, "adj_open": 12.85, "adj_volume": 1205793.0, "symbol": "NRF", "exchange": "XNYS", "date": "2016-07-25T00:00:00+0000"}, {"open": 12.86, "high": 12.98, "low": 12.78, "close": 12.83, "volume": 1768178.0, "adj_high": 12.98, "adj_low": 12.78, "adj_close": 12.83, "adj_open": 12.86, "adj_volume": 1768178.0, "symbol": "NRF", "exchange": "XNYS", "date": "2016-07-26T00:00:00+0000"}, {"open": 12.83, "high": 13.08, "low": 12.82, "close": 12.99, "volume": 1583545.0, "adj_high": 13.08, "adj_low": 12.82, "adj_close": 12.99, "adj_open": 12.83, "adj_volume": 1583545.0, "symbol": "NRF", "exchange": "XNYS", "date": "2016-07-27T00:00:00+0000"}, {"open": 13.02, "high": 13.3, "low": 12.89, "close": 13.3, "volume": 1456562.0, "adj_high": 13.3, "adj_low": 12.89, "adj_close": 13.3, "adj_open": 13.02, "adj_volume": 1456562.0, "symbol": "NRF", "exchange": "XNYS", "date": "2016-07-28T00:00:00+0000"}, {"open": 13.3, "high": 13.535, "low": 13.211, "close": 13.4, "volume": 1445513.0, "adj_high": 13.535, "adj_low": 13.211, "adj_close": 13.4, "adj_open": 13.3, "adj_volume": 1445513.0, "symbol": "NRF", "exchange": "XNYS", "date": "2016-07-29T00:00:00+0000"}, {"open": 13.4, "high": 13.6, "low": 13.29, "close": 13.32, "volume": 1262863.0, "adj_high": 13.6, "adj_low": 13.29, "adj_close": 13.32, "adj_open": 13.4, "adj_volume": 1262863.0, "symbol": "NRF", "exchange": "XNYS", "date": "2016-08-01T00:00:00+0000"}, {"open": 13.34, "high": 13.4, "low": 13.05, "close": 13.19, "volume": 1286283.0, "adj_high": 13.4, "adj_low": 13.05, "adj_close": 13.19, "adj_open": 13.34, "adj_volume": 1286283.0, "symbol": "NRF", "exchange": "XNYS", "date": "2016-08-02T00:00:00+0000"}, {"open": 13.12, "high": 13.59, "low": 13.12, "close": 13.51, "volume": 1978378.0, "adj_high": 13.59, "adj_low": 13.12, "adj_close": 13.51, "adj_open": 13.12, "adj_volume": 1978378.0, "symbol": "NRF", "exchange": "XNYS", "date": "2016-08-03T00:00:00+0000"}, {"open": 13.66, "high": 13.73, "low": 13.3, "close": 13.6, "volume": 1575468.0, "adj_high": 13.73, "adj_low": 13.3, "adj_close": 13.6, "adj_open": 13.66, "adj_volume": 1575468.0, "symbol": "NRF", "exchange": "XNYS", "date": "2016-08-04T00:00:00+0000"}, {"open": 13.58, "high": 13.79, "low": 13.49, "close": 13.71, "volume": 1116952.0, "adj_high": 13.79, "adj_low": 13.49, "adj_close": 13.71, "adj_open": 13.58, "adj_volume": 1116952.0, "symbol": "NRF", "exchange": "XNYS", "date": "2016-08-05T00:00:00+0000"}, {"open": 13.8, "high": 13.89, "low": 13.66, "close": 13.7, "volume": 2080704.0, "adj_high": 13.89, "adj_low": 13.66, "adj_close": 13.7, "adj_open": 13.8, "adj_volume": 2080704.0, "symbol": "NRF", "exchange": "XNYS", "date": "2016-08-08T00:00:00+0000"}, {"open": 13.71, "high": 13.87, "low": 13.51, "close": 13.52, "volume": 2121059.0, "adj_high": 13.87, "adj_low": 13.51, "adj_close": 13.52, "adj_open": 13.71, "adj_volume": 2121059.0, "symbol": "NRF", "exchange": "XNYS", "date": "2016-08-09T00:00:00+0000"}, {"open": 13.18, "high": 13.39, "low": 13.125, "close": 13.14, "volume": 1744657.0, "adj_high": 13.39, "adj_low": 13.125, "adj_close": 13.14, "adj_open": 13.18, "adj_volume": 1744657.0, "symbol": "NRF", "exchange": "XNYS", "date": "2016-08-11T00:00:00+0000"}, {"open": 13.13, "high": 13.29, "low": 13.07, "close": 13.09, "volume": 1133026.0, "adj_high": 13.29, "adj_low": 13.07, "adj_close": 13.09, "adj_open": 13.13, "adj_volume": 1133026.0, "symbol": "NRF", "exchange": "XNYS", "date": "2016-08-12T00:00:00+0000"}, {"open": 13.12, "high": 13.46, "low": 13.1, "close": 13.31, "volume": 1131412.0, "adj_high": 13.46, "adj_low": 13.1, "adj_close": 13.31, "adj_open": 13.12, "adj_volume": 1131412.0, "symbol": "NRF", "exchange": "XNYS", "date": "2016-08-15T00:00:00+0000"}, {"open": 13.38, "high": 13.44, "low": 13.26, "close": 13.39, "volume": 1001329.0, "adj_high": 13.44, "adj_low": 13.26, "adj_close": 13.39, "adj_open": 13.38, "adj_volume": 1001329.0, "symbol": "NRF", "exchange": "XNYS", "date": "2016-08-16T00:00:00+0000"}, {"open": 13.38, "high": 13.44, "low": 13.25, "close": 13.36, "volume": 1001487.0, "adj_high": 13.44, "adj_low": 13.25, "adj_close": 13.36, "adj_open": 13.38, "adj_volume": 1001487.0, "symbol": "NRF", "exchange": "XNYS", "date": "2016-08-17T00:00:00+0000"}, {"open": 13.41, "high": 13.52, "low": 13.385, "close": 13.44, "volume": 1373981.0, "adj_high": 13.52, "adj_low": 13.385, "adj_close": 13.44, "adj_open": 13.41, "adj_volume": 1373981.0, "symbol": "NRF", "exchange": "XNYS", "date": "2016-08-18T00:00:00+0000"}, {"open": 13.51, "high": 13.52, "low": 13.22, "close": 13.35, "volume": 1120657.0, "adj_high": 13.52, "adj_low": 13.22, "adj_close": 13.35, "adj_open": 13.51, "adj_volume": 1120657.0, "symbol": "NRF", "exchange": "XNYS", "date": "2016-08-19T00:00:00+0000"}, {"open": 13.31, "high": 13.35, "low": 12.99, "close": 13.0, "volume": 2974530.0, "adj_high": 13.35, "adj_low": 12.99, "adj_close": 13.0, "adj_open": 13.31, "adj_volume": 2974530.0, "symbol": "NRF", "exchange": "XNYS", "date": "2016-08-22T00:00:00+0000"}, {"open": 13.08, "high": 13.2, "low": 13.01, "close": 13.09, "volume": 1606926.0, "adj_high": 13.2, "adj_low": 13.01, "adj_close": 13.09, "adj_open": 13.08, "adj_volume": 1606926.0, "symbol": "NRF", "exchange": "XNYS", "date": "2016-08-23T00:00:00+0000"}, {"open": 13.1, "high": 13.18, "low": 12.98, "close": 13.03, "volume": 1436734.0, "adj_high": 13.18, "adj_low": 12.98, "adj_close": 13.03, "adj_open": 13.1, "adj_volume": 1436734.0, "symbol": "NRF", "exchange": "XNYS", "date": "2016-08-24T00:00:00+0000"}, {"open": 13.02, "high": 13.12, "low": 12.94, "close": 12.98, "volume": 853149.0, "adj_high": 13.12, "adj_low": 12.94, "adj_close": 12.98, "adj_open": 13.02, "adj_volume": 853149.0, "symbol": "NRF", "exchange": "XNYS", "date": "2016-08-25T00:00:00+0000"}, {"open": 13.03, "high": 13.15, "low": 12.84, "close": 12.85, "volume": 1538049.0, "adj_high": 13.15, "adj_low": 12.84, "adj_close": 12.85, "adj_open": 13.03, "adj_volume": 1538049.0, "symbol": "NRF", "exchange": "XNYS", "date": "2016-08-26T00:00:00+0000"}, {"open": 12.89, "high": 13.11, "low": 12.89, "close": 13.02, "volume": 865324.0, "adj_high": 13.11, "adj_low": 12.89, "adj_close": 13.02, "adj_open": 12.89, "adj_volume": 865324.0, "symbol": "NRF", "exchange": "XNYS", "date": "2016-08-29T00:00:00+0000"}, {"open": 13.06, "high": 13.2599, "low": 12.99, "close": 13.19, "volume": 544766.0, "adj_high": 13.2599, "adj_low": 12.99, "adj_close": 13.19, "adj_open": 13.06, "adj_volume": 544766.0, "symbol": "NRF", "exchange": "XNYS", "date": "2016-08-30T00:00:00+0000"}, {"open": 13.21, "high": 13.41, "low": 13.19, "close": 13.34, "volume": 2170893.0, "adj_high": 13.41, "adj_low": 13.19, "adj_close": 13.34, "adj_open": 13.21, "adj_volume": 2170893.0, "symbol": "NRF", "exchange": "XNYS", "date": "2016-08-31T00:00:00+0000"}, {"open": 13.35, "high": 13.43, "low": 13.21, "close": 13.29, "volume": 1048433.0, "adj_high": 13.43, "adj_low": 13.21, "adj_close": 13.29, "adj_open": 13.35, "adj_volume": 1048433.0, "symbol": "NRF", "exchange": "XNYS", "date": "2016-09-01T00:00:00+0000"}, {"open": 13.4, "high": 13.59, "low": 13.4, "close": 13.5, "volume": 1115700.0, "adj_high": 13.59, "adj_low": 13.4, "adj_close": 13.5, "adj_open": 13.4, "adj_volume": 1115700.0, "symbol": "NRF", "exchange": "XNYS", "date": "2016-09-02T00:00:00+0000"}, {"open": 13.48, "high": 13.6, "low": 13.45, "close": 13.52, "volume": 2387677.0, "adj_high": 13.6, "adj_low": 13.45, "adj_close": 13.52, "adj_open": 13.48, "adj_volume": 2387677.0, "symbol": "NRF", "exchange": "XNYS", "date": "2016-09-06T00:00:00+0000"}, {"open": 13.42, "high": 13.86, "low": 13.42, "close": 13.85, "volume": 2692553.0, "adj_high": 13.86, "adj_low": 13.42, "adj_close": 13.85, "adj_open": 13.42, "adj_volume": 2692553.0, "symbol": "NRF", "exchange": "XNYS", "date": "2016-09-07T00:00:00+0000"}, {"open": 13.86, "high": 13.86, "low": 13.6, "close": 13.6, "volume": 1012405.0, "adj_high": 13.86, "adj_low": 13.6, "adj_close": 13.6, "adj_open": 13.86, "adj_volume": 1012405.0, "symbol": "NRF", "exchange": "XNYS", "date": "2016-09-08T00:00:00+0000"}, {"open": 13.48, "high": 13.55, "low": 12.89, "close": 13.01, "volume": 2569190.0, "adj_high": 13.55, "adj_low": 12.89, "adj_close": 13.01, "adj_open": 13.48, "adj_volume": 2569190.0, "symbol": "NRF", "exchange": "XNYS", "date": "2016-09-09T00:00:00+0000"}, {"open": 12.93, "high": 13.28, "low": 12.75, "close": 13.19, "volume": 1759143.0, "adj_high": 13.28, "adj_low": 12.75, "adj_close": 13.19, "adj_open": 12.93, "adj_volume": 1759143.0, "symbol": "NRF", "exchange": "XNYS", "date": "2016-09-12T00:00:00+0000"}, {"open": 13.09, "high": 13.13, "low": 12.61, "close": 12.69, "volume": 2135823.0, "adj_high": 13.13, "adj_low": 12.61, "adj_close": 12.69, "adj_open": 13.09, "adj_volume": 2135823.0, "symbol": "NRF", "exchange": "XNYS", "date": "2016-09-13T00:00:00+0000"}, {"open": 12.7, "high": 12.89, "low": 12.6, "close": 12.62, "volume": 927184.0, "adj_high": 12.89, "adj_low": 12.6, "adj_close": 12.62, "adj_open": 12.7, "adj_volume": 927184.0, "symbol": "NRF", "exchange": "XNYS", "date": "2016-09-14T00:00:00+0000"}, {"open": 12.65, "high": 12.84, "low": 12.48, "close": 12.78, "volume": 1195937.0, "adj_high": 12.84, "adj_low": 12.48, "adj_close": 12.78, "adj_open": 12.65, "adj_volume": 1195937.0, "symbol": "NRF", "exchange": "XNYS", "date": "2016-09-15T00:00:00+0000"}, {"open": 12.65, "high": 12.92, "low": 12.65, "close": 12.77, "volume": 2388330.0, "adj_high": 12.92, "adj_low": 12.65, "adj_close": 12.77, "adj_open": 12.65, "adj_volume": 2388330.0, "symbol": "NRF", "exchange": "XNYS", "date": "2016-09-16T00:00:00+0000"}, {"open": 12.88, "high": 13.06, "low": 12.81, "close": 12.86, "volume": 2485291.0, "adj_high": 13.06, "adj_low": 12.81, "adj_close": 12.86, "adj_open": 12.88, "adj_volume": 2485291.0, "symbol": "NRF", "exchange": "XNYS", "date": "2016-09-19T00:00:00+0000"}, {"open": 12.93, "high": 12.94, "low": 12.51, "close": 12.55, "volume": 2542689.0, "adj_high": 12.94, "adj_low": 12.51, "adj_close": 12.55, "adj_open": 12.93, "adj_volume": 2542689.0, "symbol": "NRF", "exchange": "XNYS", "date": "2016-09-20T00:00:00+0000"}, {"open": 12.67, "high": 12.75, "low": 12.4252, "close": 12.7, "volume": 1653266.0, "adj_high": 12.75, "adj_low": 12.4252, "adj_close": 12.7, "adj_open": 12.67, "adj_volume": 1653266.0, "symbol": "NRF", "exchange": "XNYS", "date": "2016-09-21T00:00:00+0000"}, {"open": 12.83, "high": 12.965, "low": 12.81, "close": 12.88, "volume": 2217585.0, "adj_high": 12.965, "adj_low": 12.81, "adj_close": 12.88, "adj_open": 12.83, "adj_volume": 2217585.0, "symbol": "NRF", "exchange": "XNYS", "date": "2016-09-22T00:00:00+0000"}, {"open": 12.82, "high": 12.89, "low": 12.7, "close": 12.85, "volume": 1279843.0, "adj_high": 12.89, "adj_low": 12.7, "adj_close": 12.85, "adj_open": 12.82, "adj_volume": 1279843.0, "symbol": "NRF", "exchange": "XNYS", "date": "2016-09-23T00:00:00+0000"}, {"open": 12.82, "high": 12.97, "low": 12.76, "close": 12.86, "volume": 986076.0, "adj_high": 12.97, "adj_low": 12.76, "adj_close": 12.86, "adj_open": 12.82, "adj_volume": 986076.0, "symbol": "NRF", "exchange": "XNYS", "date": "2016-09-26T00:00:00+0000"}, {"open": 12.82, "high": 12.895, "low": 12.7, "close": 12.77, "volume": 1623139.0, "adj_high": 12.895, "adj_low": 12.7, "adj_close": 12.77, "adj_open": 12.82, "adj_volume": 1623139.0, "symbol": "NRF", "exchange": "XNYS", "date": "2016-09-27T00:00:00+0000"}, {"open": 12.98, "high": 13.31, "low": 12.88, "close": 13.17, "volume": 1714239.0, "adj_high": 13.31, "adj_low": 12.88, "adj_close": 13.17, "adj_open": 12.98, "adj_volume": 1714239.0, "symbol": "NRF", "exchange": "XNYS", "date": "2016-09-30T00:00:00+0000"}, {"open": 13.13, "high": 13.23, "low": 12.91, "close": 13.17, "volume": 1333903.0, "adj_high": 13.23, "adj_low": 12.91, "adj_close": 13.17, "adj_open": 13.13, "adj_volume": 1333903.0, "symbol": "NRF", "exchange": "XNYS", "date": "2016-10-03T00:00:00+0000"}, {"open": 13.19, "high": 13.27, "low": 13.05, "close": 13.26, "volume": 1662696.0, "adj_high": 13.27, "adj_low": 13.05, "adj_close": 13.26, "adj_open": 13.19, "adj_volume": 1662696.0, "symbol": "NRF", "exchange": "XNYS", "date": "2016-10-04T00:00:00+0000"}, {"open": 13.3, "high": 13.37, "low": 13.05, "close": 13.23, "volume": 5136490.0, "adj_high": 13.37, "adj_low": 13.05, "adj_close": 13.23, "adj_open": 13.3, "adj_volume": 5136490.0, "symbol": "NRF", "exchange": "XNYS", "date": "2016-10-05T00:00:00+0000"}, {"open": 13.23, "high": 13.35, "low": 13.09, "close": 13.17, "volume": 2925430.0, "adj_high": 13.35, "adj_low": 13.09, "adj_close": 13.17, "adj_open": 13.23, "adj_volume": 2925430.0, "symbol": "NRF", "exchange": "XNYS", "date": "2016-10-06T00:00:00+0000"}, {"open": 13.13, "high": 13.35, "low": 12.89, "close": 12.9, "volume": 3097348.0, "adj_high": 13.35, "adj_low": 12.89, "adj_close": 12.9, "adj_open": 13.13, "adj_volume": 3097348.0, "symbol": "NRF", "exchange": "XNYS", "date": "2016-10-07T00:00:00+0000"}, {"open": 12.97, "high": 13.16, "low": 12.95, "close": 13.13, "volume": 495603.0, "adj_high": 13.16, "adj_low": 12.95, "adj_close": 13.13, "adj_open": 12.97, "adj_volume": 495603.0, "symbol": "NRF", "exchange": "XNYS", "date": "2016-10-10T00:00:00+0000"}, {"open": 13.05, "high": 13.17, "low": 13.0, "close": 13.1, "volume": 797786.0, "adj_high": 13.17, "adj_low": 13.0, "adj_close": 13.1, "adj_open": 13.05, "adj_volume": 797786.0, "symbol": "NRF", "exchange": "XNYS", "date": "2016-10-11T00:00:00+0000"}, {"open": 13.12, "high": 13.63, "low": 13.08, "close": 13.61, "volume": 2275522.0, "adj_high": 13.63, "adj_low": 13.08, "adj_close": 13.61, "adj_open": 13.12, "adj_volume": 2275522.0, "symbol": "NRF", "exchange": "XNYS", "date": "2016-10-17T00:00:00+0000"}, {"open": 13.62, "high": 14.225, "low": 13.62, "close": 14.09, "volume": 4383071.0, "adj_high": 14.225, "adj_low": 13.62, "adj_close": 14.09, "adj_open": 13.62, "adj_volume": 4383071.0, "symbol": "NRF", "exchange": "XNYS", "date": "2016-10-18T00:00:00+0000"}, {"open": 14.15, "high": 14.2, "low": 14.0, "close": 14.07, "volume": 2471358.0, "adj_high": 14.2, "adj_low": 14.0, "adj_close": 14.07, "adj_open": 14.15, "adj_volume": 2471358.0, "symbol": "NRF", "exchange": "XNYS", "date": "2016-10-19T00:00:00+0000"}, {"open": 14.07, "high": 14.255, "low": 14.0115, "close": 14.22, "volume": 1231623.0, "adj_high": 14.255, "adj_low": 14.0115, "adj_close": 14.22, "adj_open": 14.07, "adj_volume": 1231623.0, "symbol": "NRF", "exchange": "XNYS", "date": "2016-10-20T00:00:00+0000"}, {"open": 14.4, "high": 14.63, "low": 14.25, "close": 14.54, "volume": 1825979.0, "adj_high": 14.63, "adj_low": 14.25, "adj_close": 14.54, "adj_open": 14.4, "adj_volume": 1825979.0, "symbol": "NRF", "exchange": "XNYS", "date": "2016-10-21T00:00:00+0000"}, {"open": 14.67, "high": 14.84, "low": 14.64, "close": 14.7, "volume": 1322110.0, "adj_high": 14.84, "adj_low": 14.64, "adj_close": 14.7, "adj_open": 14.67, "adj_volume": 1322110.0, "symbol": "NRF", "exchange": "XNYS", "date": "2016-10-24T00:00:00+0000"}, {"open": 14.67, "high": 14.92, "low": 14.53, "close": 14.88, "volume": 1772019.0, "adj_high": 14.92, "adj_low": 14.53, "adj_close": 14.88, "adj_open": 14.67, "adj_volume": 1772019.0, "symbol": "NRF", "exchange": "XNYS", "date": "2016-10-25T00:00:00+0000"}, {"open": 14.75, "high": 14.91, "low": 14.61, "close": 14.78, "volume": 1997192.0, "adj_high": 14.91, "adj_low": 14.61, "adj_close": 14.78, "adj_open": 14.75, "adj_volume": 1997192.0, "symbol": "NRF", "exchange": "XNYS", "date": "2016-10-26T00:00:00+0000"}, {"open": 14.76, "high": 14.84, "low": 14.28, "close": 14.3, "volume": 4358117.0, "adj_high": 14.84, "adj_low": 14.28, "adj_close": 14.3, "adj_open": 14.76, "adj_volume": 4358117.0, "symbol": "NRF", "exchange": "XNYS", "date": "2016-10-27T00:00:00+0000"}, {"open": 14.31, "high": 14.52, "low": 14.09, "close": 14.2, "volume": 2989501.0, "adj_high": 14.52, "adj_low": 14.09, "adj_close": 14.2, "adj_open": 14.31, "adj_volume": 2989501.0, "symbol": "NRF", "exchange": "XNYS", "date": "2016-10-28T00:00:00+0000"}, {"open": 15.1, "high": 15.15, "low": 14.88, "close": 14.96, "volume": 1116675.0, "adj_high": 15.15, "adj_low": 14.88, "adj_close": 14.96, "adj_open": 15.1, "adj_volume": 1116675.0, "symbol": "NRF", "exchange": "XNYS", "date": "2016-12-01T00:00:00+0000"}, {"open": 15.03, "high": 15.26, "low": 14.95, "close": 15.02, "volume": 983004.0, "adj_high": 15.26, "adj_low": 14.95, "adj_close": 15.02, "adj_open": 15.03, "adj_volume": 983004.0, "symbol": "NRF", "exchange": "XNYS", "date": "2016-12-02T00:00:00+0000"}, {"open": 15.1, "high": 15.395, "low": 15.08, "close": 15.35, "volume": 1766509.0, "adj_high": 15.395, "adj_low": 15.08, "adj_close": 15.35, "adj_open": 15.1, "adj_volume": 1766509.0, "symbol": "NRF", "exchange": "XNYS", "date": "2016-12-05T00:00:00+0000"}, {"open": 15.21, "high": 15.25, "low": 14.93, "close": 15.2, "volume": 2313036.0, "adj_high": 15.25, "adj_low": 14.93, "adj_close": 15.2, "adj_open": 15.21, "adj_volume": 2313036.0, "symbol": "NRF", "exchange": "XNYS", "date": "2016-12-06T00:00:00+0000"}, {"open": 15.27, "high": 15.45, "low": 15.13, "close": 15.41, "volume": 1397648.0, "adj_high": 15.45, "adj_low": 15.13, "adj_close": 15.41, "adj_open": 15.27, "adj_volume": 1397648.0, "symbol": "NRF", "exchange": "XNYS", "date": "2016-12-07T00:00:00+0000"}, {"open": 15.45, "high": 15.45, "low": 15.26, "close": 15.36, "volume": 1127231.0, "adj_high": 15.45, "adj_low": 15.26, "adj_close": 15.36, "adj_open": 15.45, "adj_volume": 1127231.0, "symbol": "NRF", "exchange": "XNYS", "date": "2016-12-08T00:00:00+0000"}, {"open": 15.34, "high": 15.6, "low": 15.3, "close": 15.47, "volume": 1667498.0, "adj_high": 15.6, "adj_low": 15.3, "adj_close": 15.47, "adj_open": 15.34, "adj_volume": 1667498.0, "symbol": "NRF", "exchange": "XNYS", "date": "2016-12-09T00:00:00+0000"}, {"open": 15.48, "high": 15.52, "low": 15.18, "close": 15.39, "volume": 1020658.0, "adj_high": 15.52, "adj_low": 15.18, "adj_close": 15.39, "adj_open": 15.48, "adj_volume": 1020658.0, "symbol": "NRF", "exchange": "XNYS", "date": "2016-12-12T00:00:00+0000"}, {"open": 15.37, "high": 15.5, "low": 14.95, "close": 15.05, "volume": 1897266.0, "adj_high": 15.5, "adj_low": 14.95, "adj_close": 15.05, "adj_open": 15.37, "adj_volume": 1897266.0, "symbol": "NRF", "exchange": "XNYS", "date": "2016-12-13T00:00:00+0000"}, {"open": 15.06, "high": 15.1, "low": 14.725, "close": 14.84, "volume": 1474811.0, "adj_high": 15.1, "adj_low": 14.725, "adj_close": 14.84, "adj_open": 15.06, "adj_volume": 1474811.0, "symbol": "NRF", "exchange": "XNYS", "date": "2016-12-14T00:00:00+0000"}, {"open": 14.84, "high": 14.9, "low": 14.67, "close": 14.71, "volume": 1181327.0, "adj_high": 14.9, "adj_low": 14.67, "adj_close": 14.71, "adj_open": 14.84, "adj_volume": 1181327.0, "symbol": "NRF", "exchange": "XNYS", "date": "2016-12-15T00:00:00+0000"}, {"open": 14.82, "high": 15.28, "low": 14.82, "close": 15.13, "volume": 3060827.0, "adj_high": 15.28, "adj_low": 14.82, "adj_close": 15.13, "adj_open": 14.82, "adj_volume": 3060827.0, "symbol": "NRF", "exchange": "XNYS", "date": "2016-12-16T00:00:00+0000"}, {"open": 15.13, "high": 15.2634, "low": 15.075, "close": 15.2, "volume": 1518022.0, "adj_high": 15.2634, "adj_low": 15.075, "adj_close": 15.2, "adj_open": 15.13, "adj_volume": 1518022.0, "symbol": "NRF", "exchange": "XNYS", "date": "2016-12-19T00:00:00+0000"}, {"open": 15.16, "high": 15.31, "low": 15.145, "close": 15.24, "volume": 1184889.0, "adj_high": 15.31, "adj_low": 15.145, "adj_close": 15.24, "adj_open": 15.16, "adj_volume": 1184889.0, "symbol": "NRF", "exchange": "XNYS", "date": "2016-12-20T00:00:00+0000"}, {"open": 15.26, "high": 15.595, "low": 15.24, "close": 15.39, "volume": 2669234.0, "adj_high": 15.595, "adj_low": 15.24, "adj_close": 15.39, "adj_open": 15.26, "adj_volume": 2669234.0, "symbol": "NRF", "exchange": "XNYS", "date": "2016-12-21T00:00:00+0000"}, {"open": 15.31, "high": 15.37, "low": 14.92, "close": 14.99, "volume": 2734887.0, "adj_high": 15.37, "adj_low": 14.92, "adj_close": 14.99, "adj_open": 15.31, "adj_volume": 2734887.0, "symbol": "NRF", "exchange": "XNYS", "date": "2016-12-22T00:00:00+0000"}, {"open": 15.02, "high": 15.4, "low": 14.98, "close": 15.3, "volume": 1744174.0, "adj_high": 15.4, "adj_low": 14.98, "adj_close": 15.3, "adj_open": 15.02, "adj_volume": 1744174.0, "symbol": "NRF", "exchange": "XNYS", "date": "2016-12-23T00:00:00+0000"}, {"open": 15.3, "high": 15.35, "low": 15.145, "close": 15.2, "volume": 786700.0, "adj_high": 15.35, "adj_low": 15.145, "adj_close": 15.2, "adj_open": 15.3, "adj_volume": 786700.0, "symbol": "NRF", "exchange": "XNYS", "date": "2016-12-27T00:00:00+0000"}, {"open": 15.2, "high": 15.265, "low": 15.0, "close": 15.02, "volume": 1429133.0, "adj_high": 15.265, "adj_low": 15.0, "adj_close": 15.02, "adj_open": 15.2, "adj_volume": 1429133.0, "symbol": "NRF", "exchange": "XNYS", "date": "2016-12-28T00:00:00+0000"}, {"open": 15.0, "high": 15.15, "low": 14.73, "close": 15.13, "volume": 2048806.0, "adj_high": 15.15, "adj_low": 14.73, "adj_close": 15.13, "adj_open": 15.0, "adj_volume": 2048806.0, "symbol": "NRF", "exchange": "XNYS", "date": "2016-12-29T00:00:00+0000"}, {"open": 15.13, "high": 15.17, "low": 15.0, "close": 15.15, "volume": 1981060.0, "adj_high": 15.17, "adj_low": 15.0, "adj_close": 15.15, "adj_open": 15.13, "adj_volume": 1981060.0, "symbol": "NRF", "exchange": "XNYS", "date": "2016-12-30T00:00:00+0000"}, {"open": 15.25, "high": 16.21, "low": 15.2, "close": 16.2, "volume": 3859522.0, "adj_high": 16.21, "adj_low": 15.2, "adj_close": 16.2, "adj_open": 15.25, "adj_volume": 3859522.0, "symbol": "NRF", "exchange": "XNYS", "date": "2017-01-03T00:00:00+0000"}, {"open": 16.15, "high": 16.435, "low": 16.0, "close": 16.38, "volume": 3237591.0, "adj_high": 16.435, "adj_low": 16.0, "adj_close": 16.38, "adj_open": 16.15, "adj_volume": 3237591.0, "symbol": "NRF", "exchange": "XNYS", "date": "2017-01-04T00:00:00+0000"}, {"open": 16.31, "high": 16.48, "low": 16.11, "close": 16.26, "volume": 2685802.0, "adj_high": 16.48, "adj_low": 16.11, "adj_close": 16.26, "adj_open": 16.31, "adj_volume": 2685802.0, "symbol": "NRF", "exchange": "XNYS", "date": "2017-01-05T00:00:00+0000"}, {"open": 16.1, "high": 16.335, "low": 16.07, "close": 16.22, "volume": 2956367.0, "adj_high": 16.335, "adj_low": 16.07, "adj_close": 16.22, "adj_open": 16.1, "adj_volume": 2956367.0, "symbol": "NRF", "exchange": "XNYS", "date": "2017-01-06T00:00:00+0000"}, {"open": 16.22, "high": 16.48, "low": 15.98, "close": 16.02, "volume": 3785657.0, "adj_high": 16.48, "adj_low": 15.98, "adj_close": 16.02, "adj_open": 16.22, "adj_volume": 3785657.0, "symbol": "NRF", "exchange": "XNYS", "date": "2017-01-09T00:00:00+0000"}, {"open": 15.92, "high": 16.36, "low": 15.89, "close": 16.13, "volume": 11987265.0, "adj_high": 16.36, "adj_low": 15.89, "adj_close": 16.13, "adj_open": 15.92, "adj_volume": 11987265.0, "symbol": "NRF", "exchange": "XNYS", "date": "2017-01-10T00:00:00+0000"}, {"open": 16.13, "high": 16.13, "low": 16.13, "close": 16.13, "volume": 0.0, "adj_high": 16.13, "adj_low": 16.13, "adj_close": 16.13, "adj_open": 16.13, "adj_volume": 0.0, "symbol": "NRF", "exchange": "XNYS", "date": "2017-01-11T00:00:00+0000"}, {"open": 16.13, "high": 16.13, "low": 16.13, "close": 16.13, "volume": 0.0, "adj_high": 16.13, "adj_low": 16.13, "adj_close": 16.13, "adj_open": 16.13, "adj_volume": 0.0, "symbol": "NRF", "exchange": "XNYS", "date": "2017-01-12T00:00:00+0000"}, {"open": 16.13, "high": 16.13, "low": 16.13, "close": 16.13, "volume": 0.0, "adj_high": 16.13, "adj_low": 16.13, "adj_close": 16.13, "adj_open": 16.13, "adj_volume": 0.0, "symbol": "NRF", "exchange": "XNYS", "date": "2017-01-13T00:00:00+0000"}, {"open": 16.13, "high": 16.13, "low": 16.13, "close": 16.13, "volume": 0.0, "adj_high": 16.13, "adj_low": 16.13, "adj_close": 16.13, "adj_open": 16.13, "adj_volume": 0.0, "symbol": "NRF", "exchange": "XNYS", "date": "2017-01-17T00:00:00+0000"}, {"open": 16.13, "high": 16.13, "low": 16.13, "close": 16.13, "volume": 0.0, "adj_high": 16.13, "adj_low": 16.13, "adj_close": 16.13, "adj_open": 16.13, "adj_volume": 0.0, "symbol": "NRF", "exchange": "XNYS", "date": "2017-01-18T00:00:00+0000"}]}